<?xml-stylesheet type="text/xsl" href="varreports_v3.xsl"?><data_table name="IMT_POLACK" dataset_id="pht001468.v1" study_name="Cardiovascular Health Study (CHS) Cohort" study_id="phs000287.v6" participant_set="1" date_created="12/15/2016"><description>Intima-media thickness (carotid artery)</description><variable id="phv00100863.v1.p1" var_name="Individual_ID" calculated_type="string" reported_type="string"><description>Subject Identifier</description><total><subject_profile><sex><male>2375</male><female>3156</female></sex></subject_profile><stats><stat n="5531" nulls="0"/></stats></total></variable><variable id="phv00100863.v1.p1.c1" var_name="Individual_ID" calculated_type="string" reported_type="string"><description>Subject Identifier</description><total><subject_profile><sex><male>2307</male><female>3046</female></sex></subject_profile><stats><stat n="5353" nulls="0"/></stats></total></variable><variable id="phv00100863.v1.p1.c2" var_name="Individual_ID" calculated_type="string" reported_type="string"><description>Subject Identifier</description><total><subject_profile><sex><male>66</male><female>105</female></sex></subject_profile><stats><stat n="171" nulls="0"/></stats></total></variable><variable id="phv00100863.v1.p1.c3" var_name="Individual_ID" calculated_type="string" reported_type="string"><description>Subject Identifier</description><total><subject_profile><sex><male>1</male><female>1</female></sex></subject_profile><stats><stat n="2" nulls="0"/></stats></total></variable><variable id="phv00100863.v1.p1.c4" var_name="Individual_ID" calculated_type="string" reported_type="string"><description>Subject Identifier</description><total><subject_profile><sex><male>1</male><female>4</female></sex></subject_profile><stats><stat n="5" nulls="0"/></stats></total></variable><variable id="phv00100864.v1.p1" var_name="CCA_FWME" calculated_type="decimal" reported_type="decimal"><description>Mean of the mean far wall intima media t (var=CCA_FWME)</description><comment>Dictionaries were submitted w/some SAS file derived code definitions (extracted by T.Y. - BROAD Institute); where possible, additional code meanings were extracted from submitted document: &lt;a href="javascript:getPage(this, &amp;#39;document.cgi&amp;#39;, 2782);return true;" onclick="javascript:getPage(this, &amp;#39;document.cgi&amp;#39;, 2782);return true;" oncontextmenu="javascript:getPage(this, &amp;#39;document.cgi&amp;#39;, 2782);return true;"&gt;VALUELBL&lt;/a&gt; (or document &amp;#39;CALCULATED VARIABLES&amp;#39; [phd002771]), and inserted.</comment><total><subject_profile><sex><male>2365</male><female>3137</female></sex></subject_profile><stats><stat n="5502" nulls="29" mean="0.8651" sd="0.2137" median="0.835" min="0.44" max="2.56"/><example count="54">0.844999969</example><example count="51">0.719999969</example><example count="50">0.8799999655</example><example count="50">0.7849999665</example><example count="50">0.7799999715</example><example count="46">0.6549999715</example><example count="42">0.8099999725</example><example count="41">0.8349999785</example><example count="41">0.774999976</example><example count="40">0.7599999605</example></stats></total></variable><variable id="phv00100864.v1.p1.c1" var_name="CCA_FWME" calculated_type="decimal" reported_type="decimal"><description>Mean of the mean far wall intima media t (var=CCA_FWME)</description><comment>Dictionaries were submitted w/some SAS file derived code definitions (extracted by T.Y. - BROAD Institute); where possible, additional code meanings were extracted from submitted document: &lt;a href="javascript:getPage(this, &amp;#39;document.cgi&amp;#39;, 2782);return true;" onclick="javascript:getPage(this, &amp;#39;document.cgi&amp;#39;, 2782);return true;" oncontextmenu="javascript:getPage(this, &amp;#39;document.cgi&amp;#39;, 2782);return true;"&gt;VALUELBL&lt;/a&gt; (or document &amp;#39;CALCULATED VARIABLES&amp;#39; [phd002771]), and inserted.</comment><total><subject_profile><sex><male>2297</male><female>3027</female></sex></subject_profile><stats><stat n="5324" nulls="29" mean="0.8667" sd="0.2143" median="0.835" min="0.44" max="2.56"/><example count="53">0.844999969</example><example count="50">0.7849999665</example><example count="49">0.8799999655</example><example count="49">0.719999969</example><example count="46">0.7799999715</example><example count="44">0.6549999715</example><example count="41">0.774999976</example><example count="41">0.8099999725</example><example count="39">0.8349999785</example><example count="39">0.7549999655</example></stats></total></variable><variable id="phv00100864.v1.p1.c2" var_name="CCA_FWME" calculated_type="decimal" reported_type="decimal"><description>Mean of the mean far wall intima media t (var=CCA_FWME)</description><comment>Dictionaries were submitted w/some SAS file derived code definitions (extracted by T.Y. - BROAD Institute); where possible, additional code meanings were extracted from submitted document: &lt;a href="javascript:getPage(this, &amp;#39;document.cgi&amp;#39;, 2782);return true;" onclick="javascript:getPage(this, &amp;#39;document.cgi&amp;#39;, 2782);return true;" oncontextmenu="javascript:getPage(this, &amp;#39;document.cgi&amp;#39;, 2782);return true;"&gt;VALUELBL&lt;/a&gt; (or document &amp;#39;CALCULATED VARIABLES&amp;#39; [phd002771]), and inserted.</comment><total><subject_profile><sex><male>66</male><female>105</female></sex></subject_profile><stats><stat n="171" nulls="0" mean="0.8183" sd="0.1911" median="0.795" min="0.505" max="1.645"/><example count="4">0.7799999715</example><example count="4">0.589999974</example><example count="3">0.924999952</example><example count="3">0.639999956</example><example count="2">0.6549999715</example><example count="2">0.8099999425</example><example count="2">0.8349999785</example><example count="2">0.7049999835</example><example count="2">0.8399999735</example><example count="2">0.6999999585</example></stats></total></variable><variable id="phv00100864.v1.p1.c3" var_name="CCA_FWME" calculated_type="decimal" reported_type="decimal"><description>Mean of the mean far wall intima media t (var=CCA_FWME)</description><comment>Dictionaries were submitted w/some SAS file derived code definitions (extracted by T.Y. - BROAD Institute); where possible, additional code meanings were extracted from submitted document: &lt;a href="javascript:getPage(this, &amp;#39;document.cgi&amp;#39;, 2782);return true;" onclick="javascript:getPage(this, &amp;#39;document.cgi&amp;#39;, 2782);return true;" oncontextmenu="javascript:getPage(this, &amp;#39;document.cgi&amp;#39;, 2782);return true;"&gt;VALUELBL&lt;/a&gt; (or document &amp;#39;CALCULATED VARIABLES&amp;#39; [phd002771]), and inserted.</comment><total><subject_profile><sex><male>1</male><female>1</female></sex></subject_profile><stats><stat n="2" nulls="0" mean="0.955" sd="0.04243" median="0.955" min="0.925" max="0.985"/><enum count="1">0.9249999525</enum><enum count="1">0.9849999845</enum></stats></total></variable><variable id="phv00100864.v1.p1.c4" var_name="CCA_FWME" calculated_type="decimal" reported_type="decimal"><description>Mean of the mean far wall intima media t (var=CCA_FWME)</description><comment>Dictionaries were submitted w/some SAS file derived code definitions (extracted by T.Y. - BROAD Institute); where possible, additional code meanings were extracted from submitted document: &lt;a href="javascript:getPage(this, &amp;#39;document.cgi&amp;#39;, 2782);return true;" onclick="javascript:getPage(this, &amp;#39;document.cgi&amp;#39;, 2782);return true;" oncontextmenu="javascript:getPage(this, &amp;#39;document.cgi&amp;#39;, 2782);return true;"&gt;VALUELBL&lt;/a&gt; (or document &amp;#39;CALCULATED VARIABLES&amp;#39; [phd002771]), and inserted.</comment><total><subject_profile><sex><male>1</male><female>4</female></sex></subject_profile><stats><stat n="5" nulls="0" mean="0.792" sd="0.1702" median="0.765" min="0.575" max="1"/><enum count="1">0.9999999405</enum><enum count="1">0.7649999555</enum><enum count="1">0.5749999585</enum><enum count="1">0.699999988</enum><enum count="1">0.919999957</enum></stats></total></variable><variable id="phv00100865.v1.p1" var_name="ICA_FWME" calculated_type="decimal" reported_type="decimal"><description>Mean of the mean far wall intima-media t</description><comment>Dictionaries were submitted w/some SAS file derived code definitions (extracted by T.Y.  BROAD Institute); where possible, additional code meanings were extracted from submitted document: &lt;a href="javascript:getPage(this, &amp;#39;document.cgi&amp;#39;, 2782);return true;" onclick="javascript:getPage(this, &amp;#39;document.cgi&amp;#39;, 2782);return true;" oncontextmenu="javascript:getPage(this, &amp;#39;document.cgi&amp;#39;, 2782);return true;"&gt;VALUELBL&lt;/a&gt; (or document &amp;#39;CALCULATED VARIABLES&amp;#39; [phd002771]), and inserted.</comment><total><subject_profile><sex><male>2354</male><female>3129</female></sex></subject_profile><stats><stat n="5483" nulls="48" mean="0.9796" sd="0.4196" median="0.855" min="0.4067" max="5.41"/><example count="6">0.643333306</example><example count="6">0.7233332992</example><example count="6">0.6999999682</example><example count="6">0.7533333003</example><example count="6">0.7633333008</example><example count="6">0.7233333092</example><example count="5">0.7316666345</example><example count="5">0.8049999675</example><example count="5">0.6583333015</example><example count="5">0.7916666368</example></stats></total></variable><variable id="phv00100865.v1.p1.c1" var_name="ICA_FWME" calculated_type="decimal" reported_type="decimal"><description>Mean of the mean far wall intima-media t</description><comment>Dictionaries were submitted w/some SAS file derived code definitions (extracted by T.Y.  BROAD Institute); where possible, additional code meanings were extracted from submitted document: &lt;a href="javascript:getPage(this, &amp;#39;document.cgi&amp;#39;, 2782);return true;" onclick="javascript:getPage(this, &amp;#39;document.cgi&amp;#39;, 2782);return true;" oncontextmenu="javascript:getPage(this, &amp;#39;document.cgi&amp;#39;, 2782);return true;"&gt;VALUELBL&lt;/a&gt; (or document &amp;#39;CALCULATED VARIABLES&amp;#39; [phd002771]), and inserted.</comment><total><subject_profile><sex><male>2286</male><female>3019</female></sex></subject_profile><stats><stat n="5305" nulls="48" mean="0.982" sd="0.4165" median="0.8583" min="0.4067" max="4.49"/><example count="6">0.643333306</example><example count="6">0.7233332992</example><example count="6">0.6999999682</example><example count="6">0.7533333003</example><example count="6">0.7233333092</example><example count="5">0.7316666345</example><example count="5">0.8049999675</example><example count="5">0.6583333015</example><example count="5">0.7916666368</example><example count="5">0.7599999607</example></stats></total></variable><variable id="phv00100865.v1.p1.c2" var_name="ICA_FWME" calculated_type="decimal" reported_type="decimal"><description>Mean of the mean far wall intima-media t</description><comment>Dictionaries were submitted w/some SAS file derived code definitions (extracted by T.Y.  BROAD Institute); where possible, additional code meanings were extracted from submitted document: &lt;a href="javascript:getPage(this, &amp;#39;document.cgi&amp;#39;, 2782);return true;" onclick="javascript:getPage(this, &amp;#39;document.cgi&amp;#39;, 2782);return true;" oncontextmenu="javascript:getPage(this, &amp;#39;document.cgi&amp;#39;, 2782);return true;"&gt;VALUELBL&lt;/a&gt; (or document &amp;#39;CALCULATED VARIABLES&amp;#39; [phd002771]), and inserted.</comment><total><subject_profile><sex><male>66</male><female>105</female></sex></subject_profile><stats><stat n="171" nulls="0" mean="0.8878" sd="0.3712" median="0.7783" min="0.42" max="2.7"/><example count="2">0.5633333127</example><example count="2">0.5883332987</example><example count="1">0.597999984</example><example count="1">0.6316666403</example><example count="1">0.6549999715</example><example count="1">0.8649999648</example><example count="1">0.6849999725</example><example count="1">0.7099999785</example><example count="1">1.369999945</example><example count="1">0.8159999668</example></stats></total></variable><variable id="phv00100865.v1.p1.c3" var_name="ICA_FWME" calculated_type="decimal" reported_type="decimal"><description>Mean of the mean far wall intima-media t</description><comment>Dictionaries were submitted w/some SAS file derived code definitions (extracted by T.Y.  BROAD Institute); where possible, additional code meanings were extracted from submitted document: &lt;a href="javascript:getPage(this, &amp;#39;document.cgi&amp;#39;, 2782);return true;" onclick="javascript:getPage(this, &amp;#39;document.cgi&amp;#39;, 2782);return true;" oncontextmenu="javascript:getPage(this, &amp;#39;document.cgi&amp;#39;, 2782);return true;"&gt;VALUELBL&lt;/a&gt; (or document &amp;#39;CALCULATED VARIABLES&amp;#39; [phd002771]), and inserted.</comment><total><subject_profile><sex><male>1</male><female>1</female></sex></subject_profile><stats><stat n="2" nulls="0" mean="3.087" sd="3.286" median="3.087" min="0.7633" max="5.41"/><enum count="1">0.7633333108</enum><enum count="1">5.409999847</enum></stats></total></variable><variable id="phv00100865.v1.p1.c4" var_name="ICA_FWME" calculated_type="decimal" reported_type="decimal"><description>Mean of the mean far wall intima-media t</description><comment>Dictionaries were submitted w/some SAS file derived code definitions (extracted by T.Y.  BROAD Institute); where possible, additional code meanings were extracted from submitted document: &lt;a href="javascript:getPage(this, &amp;#39;document.cgi&amp;#39;, 2782);return true;" onclick="javascript:getPage(this, &amp;#39;document.cgi&amp;#39;, 2782);return true;" oncontextmenu="javascript:getPage(this, &amp;#39;document.cgi&amp;#39;, 2782);return true;"&gt;VALUELBL&lt;/a&gt; (or document &amp;#39;CALCULATED VARIABLES&amp;#39; [phd002771]), and inserted.</comment><total><subject_profile><sex><male>1</male><female>4</female></sex></subject_profile><stats><stat n="5" nulls="0" mean="0.748" sd="0.1695" median="0.67" min="0.5783" max="0.9917"/><enum count="1">0.669999967</enum><enum count="1">0.9916666052</enum><enum count="1">0.5783333182</enum><enum count="1">0.6483333113</enum><enum count="1">0.8516666295</enum></stats></total></variable></data_table>
