<?xml-stylesheet type="text/xsl" href="./datadict_v2.xsl"?><data_table id="pht006488.v1" study_id="phs000280.v5" participant_set="1" date_created="Mon Nov 19 12:17:06 2018"><description>Visit 5. Visit 5. Subject ID, aneurysm, plaque, adherence, RM3, LM3, RP3, LP3, RV4, LV4, quality, qualitative analysis, variant, cavernous calcification, code, RMCA, LMCA, RICA, LICA, basilar-proxy measured, v4, and A1 of participants with or without atherosclerosis and cardiovascular disease and involved in the "Atherosclerosis Risk in Communities (ARIC) Cohort" project.</description><variable id="phv00298253.v1"><name>SUBJECT_ID</name><description>ARIC subject ID</description></variable><variable id="phv00298254.v1"><name>WMRL5</name><description>Presence Of aneurysms</description></variable><variable id="phv00298255.v1"><name>WMRL6</name><description>Number Of aneurysms</description></variable><variable id="phv00298256.v1"><name>WMRL7</name><description>Maximum width of the #1 aneurysm</description><unit>Cm</unit></variable><variable id="phv00298257.v1"><name>WMRL8</name><description>Maximum depth of the #1 aneurysm</description><unit>Cm</unit></variable><variable id="phv00298258.v1"><name>WMRL9</name><description>Location of the #1 aneurysm</description></variable><variable id="phv00298259.v1"><name>WMRL10</name><description>Maximum width of the #2 aneurysm</description><unit>Cm</unit></variable><variable id="phv00298260.v1"><name>WMRL11</name><description>Maximum depth of the #2 aneurysm</description><unit>Cm</unit></variable><variable id="phv00298261.v1"><name>WMRL12</name><description>Location of the #2 aneurysm</description></variable><variable id="phv00298262.v1"><name>WMRL13</name><description>Maximum width of the #3 aneurysm</description><unit>Cm</unit></variable><variable id="phv00298263.v1"><name>WMRL14</name><description>Maximum depth of the #3 aneurysm</description><unit>Cm</unit></variable><variable id="phv00298264.v1"><name>WMRL15</name><description>Location of the #3 aneurysm</description></variable><variable id="phv00298265.v1"><name>WMRL16</name><description>Maximum width of the #4 aneurysm</description><unit>Cm</unit></variable><variable id="phv00298266.v1"><name>WMRL17</name><description>Maximum depth of the #4 aneurysm</description><unit>Cm</unit></variable><variable id="phv00298267.v1"><name>WMRL18</name><description>Location of the #4 aneurysm</description></variable><variable id="phv00298268.v1"><name>WMRL19</name><description>Maximum width of the #5 aneurysm</description><unit>Cm</unit></variable><variable id="phv00298269.v1"><name>WMRL20</name><description>Maximum depth of the #5 aneurysm</description><unit>Cm</unit></variable><variable id="phv00298270.v1"><name>WMRL21</name><description>Location of the #5 aneurysm</description></variable><variable id="phv00298271.v1"><name>WMRL22</name><description>Maximum width of the #6 aneurysm</description><unit>Cm</unit></variable><variable id="phv00298272.v1"><name>WMRL23</name><description>Maximum depth of the #6 aneurysm</description><unit>Cm</unit></variable><variable id="phv00298273.v1"><name>WMRL24</name><description>Location of the #6 aneurysm</description></variable><variable id="phv00298274.v1"><name>WMRL25</name><description>Maximum width of the #7 aneurysm</description><unit>Cm</unit></variable><variable id="phv00298275.v1"><name>WMRL26</name><description>Maximum depth of the #7 aneurysm</description><unit>Cm</unit></variable><variable id="phv00298276.v1"><name>WMRL27</name><description>Location of the #7 aneurysm</description></variable><variable id="phv00298277.v1"><name>WMRL28</name><description>Maximum width of the #8 aneurysm</description><unit>Cm</unit></variable><variable id="phv00298278.v1"><name>WMRL29</name><description>Maximum depth of the #8 aneurysm</description><unit>Cm</unit></variable><variable id="phv00298279.v1"><name>WMRL30</name><description>Location of the #8 aneurysm</description></variable><variable id="phv00298280.v1"><name>WMRL31</name><description>Maximum width of the #9 aneurysm</description><unit>Cm</unit></variable><variable id="phv00298281.v1"><name>WMRL32</name><description>Maximum depth of the #9 aneurysm</description><unit>Cm</unit></variable><variable id="phv00298282.v1"><name>WMRL33</name><description>Location of the #9 aneurysm</description></variable><variable id="phv00298283.v1"><name>WMRL34</name><description>Maximum width of the #10 aneurysm</description><unit>Cm</unit></variable><variable id="phv00298284.v1"><name>WMRL35</name><description>Maximum depth of the #10 aneurysm</description><unit>Cm</unit></variable><variable id="phv00298285.v1"><name>WMRL36</name><description>Location of the #10 aneurysm</description></variable><variable id="phv00298286.v1"><name>WMRL37</name><description>Presence of variants</description></variable><variable id="phv00298287.v1"><name>WMRL38</name><description>Number of variants</description></variable><variable id="phv00298288.v1"><name>WMRL39</name><description>Type of the # 1 variant</description></variable><variable id="phv00298289.v1"><name>WMRL40</name><description>If #1 variant others, please describe</description></variable><variable id="phv00298290.v1"><name>WMRL41</name><description>Location of the #1 variant</description></variable><variable id="phv00298291.v1"><name>WMRL42</name><description>Type of the # 2 variant</description></variable><variable id="phv00298292.v1"><name>WMRL43</name><description>If #2 variant others, please describe</description></variable><variable id="phv00298293.v1"><name>WMRL44</name><description>Location of the #2 variant</description></variable><variable id="phv00298294.v1"><name>WMRL45</name><description>Type of the # 3 variant</description></variable><variable id="phv00298295.v1"><name>WMRL46</name><description>If #3 variant others, please describe</description></variable><variable id="phv00298296.v1"><name>WMRL47</name><description>Location of the #3 variant</description></variable><variable id="phv00298297.v1"><name>WMRL48</name><description>Type of the # 4 variant</description></variable><variable id="phv00298298.v1"><name>WMRL49</name><description>If #4 variant others, please describe</description></variable><variable id="phv00298299.v1"><name>WMRL50</name><description>Location of the #4 variant</description></variable><variable id="phv00298300.v1"><name>WMRL51</name><description>Type of the # 5 variant</description></variable><variable id="phv00298301.v1"><name>WMRL52</name><description>WMRL52</description></variable><variable id="phv00298302.v1"><name>WMRL53</name><description>Location of the #5 variant</description></variable><variable id="phv00298303.v1"><name>WMRL54</name><description>Type of the # 6 variant</description></variable><variable id="phv00298304.v1"><name>WMRL55</name><description>WMRL55</description></variable><variable id="phv00298305.v1"><name>WMRL56</name><description>Location of the #6 variant</description></variable><variable id="phv00298306.v1"><name>WMRL57</name><description>Type of the # 7 variant</description></variable><variable id="phv00298307.v1"><name>WMRL58</name><description>If #7 variant others, please describe</description></variable><variable id="phv00298308.v1"><name>WMRL59</name><description>Location of the #7 variant</description></variable><variable id="phv00298309.v1"><name>WMRL60</name><description>Type of the # 8 variant</description></variable><variable id="phv00298310.v1"><name>WMRL61</name><description>If #8 variant others, please describe</description></variable><variable id="phv00298311.v1"><name>WMRL62</name><description>Location of the #8 variant</description></variable><variable id="phv00298312.v1"><name>WMRL63</name><description>Type of the # 9 variant</description></variable><variable id="phv00298313.v1"><name>WMRL64</name><description>If #9 variant others, please describe</description></variable><variable id="phv00298314.v1"><name>WMRL65</name><description>Location of the #9 variant</description></variable><variable id="phv00298315.v1"><name>WMRL66</name><description>Type of the # 10 variant</description></variable><variable id="phv00298316.v1"><name>WMRL67</name><description>If #10 variant others, please describe</description></variable><variable id="phv00298317.v1"><name>WMRL68</name><description>Location of the #10 variant</description></variable><variable id="phv00298318.v1"><name>WMRL69</name><description>Presence of plaques</description></variable><variable id="phv00298319.v1"><name>WMRL70</name><description>Number Of RMCA plaques</description></variable><variable id="phv00298320.v1"><name>WMRL71</name><description>Location of the #1 RMCA plaque</description></variable><variable id="phv00298321.v1"><name>WMRL72</name><description>Is this the most stenotic RMCA plaque? #1</description></variable><variable id="phv00298322.v1"><name>WMRL73</name><description>Location of the #2 RMCA plaque</description></variable><variable id="phv00298323.v1"><name>WMRL74</name><description>Is this the most stenotic RMCA plaque? #2</description></variable><variable id="phv00298324.v1"><name>WMRL75</name><description>Location of the #3 RMCA plaque</description></variable><variable id="phv00298325.v1"><name>WMRL76</name><description>Is this the most stenotic RMCA plaque? #3</description></variable><variable id="phv00298326.v1"><name>WMRL77</name><description>Location of the #4 RMCA plaque</description></variable><variable id="phv00298327.v1"><name>WMRL78</name><description>Is this the most stenotic RMCA plaque? #4</description></variable><variable id="phv00298328.v1"><name>WMRL79</name><description>Location of the #5 RMCA plaque</description></variable><variable id="phv00298329.v1"><name>WMRL80</name><description>Is this the most stenotic RMCA plaque? #5</description></variable><variable id="phv00298330.v1"><name>WMRL81</name><description>Location of the #6 RMCA plaque</description></variable><variable id="phv00298331.v1"><name>WMRL82</name><description>Is this the most stenotic RMCA plaque? #6</description></variable><variable id="phv00298332.v1"><name>WMRL83</name><description>Location of the #7 RMCA plaque</description></variable><variable id="phv00298333.v1"><name>WMRL84</name><description>Is this the most stenotic RMCA plaque? #7</description></variable><variable id="phv00298334.v1"><name>WMRL85</name><description>Location of the #8 RMCA plaque</description></variable><variable id="phv00298335.v1"><name>WMRL86</name><description>Is this the most stenotic RMCA plaque? #8</description></variable><variable id="phv00298336.v1"><name>WMRL87</name><description>Location of the #9 RMCA plaque</description></variable><variable id="phv00298337.v1"><name>WMRL88</name><description>Is this the most stenotic RMCA plaque? #9</description></variable><variable id="phv00298338.v1"><name>WMRL89</name><description>Location of the #10 RMCA plaque</description></variable><variable id="phv00298339.v1"><name>WMRL90</name><description>Is this the most stenotic RMCA plaque? #10</description></variable><variable id="phv00298340.v1"><name>WMRL91</name><description>Confidence factor RMCA_plaq</description></variable><variable id="phv00298341.v1"><name>WMRL92</name><description>Identified RMCA_plaq</description></variable><variable id="phv00298342.v1"><name>WMRL93</name><description>Calcification RMCA_plaq</description></variable><variable id="phv00298343.v1"><name>WMRL94</name><description>T1 Hyperintense RMCA_plaq</description></variable><variable id="phv00298344.v1"><name>WMRL95</name><description>Degree of stenosis RMCA_plaq</description></variable><variable id="phv00298345.v1"><name>WMRL96</name><description>Number Of lMCA plaques</description></variable><variable id="phv00298346.v1"><name>WMRL97</name><description>Location of the #1 lMCA plaque</description></variable><variable id="phv00298347.v1"><name>WMRL98</name><description>Is this the most stenotic lMCA plaque? #1</description></variable><variable id="phv00298348.v1"><name>WMRL99</name><description>Location of the #2 lMCA plaque</description></variable><variable id="phv00298349.v1"><name>WMRL100</name><description>Is this the most stenotic lMCA plaque? #2</description></variable><variable id="phv00298350.v1"><name>WMRL101</name><description>Location of the #3 lMCA plaque</description></variable><variable id="phv00298351.v1"><name>WMRL102</name><description>Is this the most stenotic lMCA plaque? #3</description></variable><variable id="phv00298352.v1"><name>WMRL103</name><description>Location of the #4 lMCA plaque</description></variable><variable id="phv00298353.v1"><name>WMRL104</name><description>Is this the most stenotic lMCA plaque? #4</description></variable><variable id="phv00298354.v1"><name>WMRL105</name><description>Location of the #5 lMCA plaque</description></variable><variable id="phv00298355.v1"><name>WMRL106</name><description>Is this the most stenotic lMCA plaque? #5</description></variable><variable id="phv00298356.v1"><name>WMRL107</name><description>Location of the #6 lMCA plaque</description></variable><variable id="phv00298357.v1"><name>WMRL108</name><description>Is this the most stenotic lMCA plaque? #6</description></variable><variable id="phv00298358.v1"><name>WMRL109</name><description>Location of the #7 lMCA plaque</description></variable><variable id="phv00298359.v1"><name>WMRL110</name><description>Is this the most stenotic lMCA plaque? #7</description></variable><variable id="phv00298360.v1"><name>WMRL111</name><description>Location of the #8 lMCA plaque</description></variable><variable id="phv00298361.v1"><name>WMRL112</name><description>Is this the most stenotic lMCA plaque? #8</description></variable><variable id="phv00298362.v1"><name>WMRL113</name><description>Location of the #9 lMCA plaque</description></variable><variable id="phv00298363.v1"><name>WMRL114</name><description>Is this the most stenotic lMCA plaque? #9</description></variable><variable id="phv00298364.v1"><name>WMRL115</name><description>Location of the #10 lMCA plaque</description></variable><variable id="phv00298365.v1"><name>WMRL116</name><description>Is this the most stenotic lMCA plaque? #10</description></variable><variable id="phv00298366.v1"><name>WMRL117</name><description>Confidence factor lMCA_plaq</description></variable><variable id="phv00298367.v1"><name>WMRL118</name><description>Identified lMCA_plaq</description></variable><variable id="phv00298368.v1"><name>WMRL119</name><description>Calcification lMCA_plaq</description></variable><variable id="phv00298369.v1"><name>WMRL120</name><description>T1 Hyperintense lMCA_plaq</description></variable><variable id="phv00298370.v1"><name>WMRL121</name><description>Degree of stenosis lMCA_plaq</description></variable><variable id="phv00298371.v1"><name>WMRL122</name><description>Number of RACA plaques</description></variable><variable id="phv00298372.v1"><name>WMRL123</name><description>Location of the #1 RACA plaque</description></variable><variable id="phv00298373.v1"><name>WMRL124</name><description>Is this the most stenotic RACA plaque? #1</description></variable><variable id="phv00298374.v1"><name>WMRL125</name><description>Location of the #2 RACA plaque</description></variable><variable id="phv00298375.v1"><name>WMRL126</name><description>Is this the most stenotic RACA plaque? #2</description></variable><variable id="phv00298376.v1"><name>WMRL127</name><description>Location of the #3 RACA plaque</description></variable><variable id="phv00298377.v1"><name>WMRL128</name><description>Is this the most stenotic RACA plaque? #3</description></variable><variable id="phv00298378.v1"><name>WMRL129</name><description>Location of the #4 RACA plaque</description></variable><variable id="phv00298379.v1"><name>WMRL130</name><description>Is this the most stenotic RACA plaque? #4</description></variable><variable id="phv00298380.v1"><name>WMRL131</name><description>Location of the #5 RACA plaque</description></variable><variable id="phv00298381.v1"><name>WMRL132</name><description>Is this the most stenotic RACA plaque? #5</description></variable><variable id="phv00298382.v1"><name>WMRL133</name><description>Location of the #6 RACA plaque</description></variable><variable id="phv00298383.v1"><name>WMRL134</name><description>Is this the most stenotic RACA plaque? #6</description></variable><variable id="phv00298384.v1"><name>WMRL135</name><description>Location of the #7 RACA plaque</description></variable><variable id="phv00298385.v1"><name>WMRL136</name><description>Is this the most stenotic RACA plaque? #7</description></variable><variable id="phv00298386.v1"><name>WMRL137</name><description>Location of the #8 RACA plaque</description></variable><variable id="phv00298387.v1"><name>WMRL138</name><description>Is this the most stenotic RACA plaque? #8</description></variable><variable id="phv00298388.v1"><name>WMRL139</name><description>Location of the #9 RACA plaque</description></variable><variable id="phv00298389.v1"><name>WMRL140</name><description>Is this the most stenotic RACA plaque? #9</description></variable><variable id="phv00298390.v1"><name>WMRL141</name><description>Location of the #10 RACA plaque</description></variable><variable id="phv00298391.v1"><name>WMRL142</name><description>Is this the most stenotic RACA plaque? #10</description></variable><variable id="phv00298392.v1"><name>WMRL143</name><description>Confidence factor Raca_plaq</description></variable><variable id="phv00298393.v1"><name>WMRL144</name><description>Identified Raca_plaq</description></variable><variable id="phv00298394.v1"><name>WMRL145</name><description>Calcification Raca_plaq</description></variable><variable id="phv00298395.v1"><name>WMRL146</name><description>T1 Hyperintense Raca_plaq</description></variable><variable id="phv00298396.v1"><name>WMRL147</name><description>Degree of stenosis Raca_plaq</description></variable><variable id="phv00298397.v1"><name>WMRL148</name><description>Number of LACA plaques</description></variable><variable id="phv00298398.v1"><name>WMRL149</name><description>Location of the #1 LACA plaque</description></variable><variable id="phv00298399.v1"><name>WMRL150</name><description>Is this the most stenotic LACA plaque? #1</description></variable><variable id="phv00298400.v1"><name>WMRL151</name><description>Location of the #2 LACA plaque</description></variable><variable id="phv00298401.v1"><name>WMRL152</name><description>Is this the most stenotic LACA plaque? #2</description></variable><variable id="phv00298402.v1"><name>WMRL153</name><description>Location of the #3 LACA plaque</description></variable><variable id="phv00298403.v1"><name>WMRL154</name><description>Is this the most stenotic LACA plaque? #3</description></variable><variable id="phv00298404.v1"><name>WMRL155</name><description>Location of the #4 LACA plaque</description></variable><variable id="phv00298405.v1"><name>WMRL156</name><description>Is this the most stenotic LACA plaque? #4</description></variable><variable id="phv00298406.v1"><name>WMRL157</name><description>Location of the #5 LACA plaque</description></variable><variable id="phv00298407.v1"><name>WMRL158</name><description>Is this the most stenotic LACA plaque? #5</description></variable><variable id="phv00298408.v1"><name>WMRL159</name><description>Location of the #6 LACA plaque</description></variable><variable id="phv00298409.v1"><name>WMRL160</name><description>Is this the most stenotic LACA plaque? #6</description></variable><variable id="phv00298410.v1"><name>WMRL161</name><description>Location of the #7 LACA plaque</description></variable><variable id="phv00298411.v1"><name>WMRL162</name><description>Is this the most stenotic LACA plaque? #7</description></variable><variable id="phv00298412.v1"><name>WMRL163</name><description>Location of the #8 LACA plaque</description></variable><variable id="phv00298413.v1"><name>WMRL164</name><description>Is this the most stenotic LACA plaque? #8</description></variable><variable id="phv00298414.v1"><name>WMRL165</name><description>Location of the #9 LACA plaque</description></variable><variable id="phv00298415.v1"><name>WMRL166</name><description>Is this the most stenotic LACA plaque? #9</description></variable><variable id="phv00298416.v1"><name>WMRL167</name><description>Location of the #10 LACA plaque</description></variable><variable id="phv00298417.v1"><name>WMRL168</name><description>Is this the most stenotic LACA plaque? #10</description></variable><variable id="phv00298418.v1"><name>WMRL169</name><description>Confidence factor Laca_plaq</description></variable><variable id="phv00298419.v1"><name>WMRL170</name><description>Identified Laca_plaq</description></variable><variable id="phv00298420.v1"><name>WMRL171</name><description>Calcification Laca_paq</description></variable><variable id="phv00298421.v1"><name>WMRL172</name><description>T1 Hyperintense Laca_plaq</description></variable><variable id="phv00298422.v1"><name>WMRL173</name><description>Degree of stenosis Laca_plaq</description></variable><variable id="phv00298423.v1"><name>WMRL174</name><description>Number of RICA plaques</description></variable><variable id="phv00298424.v1"><name>WMRL175</name><description>Location of the #1 RICA plaque</description></variable><variable id="phv00298425.v1"><name>WMRL176</name><description>Is this the most stenotic RICA plaque? #1</description></variable><variable id="phv00298426.v1"><name>WMRL177</name><description>Location of the #2 RICA plaque</description></variable><variable id="phv00298427.v1"><name>WMRL178</name><description>Is this the most stenotic RICA plaque? #2</description></variable><variable id="phv00298428.v1"><name>WMRL179</name><description>Location of the #3 RICA plaque</description></variable><variable id="phv00298429.v1"><name>WMRL180</name><description>Is this the most stenotic RICA plaque? #3</description></variable><variable id="phv00298430.v1"><name>WMRL181</name><description>Location of the #4 RICA plaque</description></variable><variable id="phv00298431.v1"><name>WMRL182</name><description>Is this the most stenotic RICA plaque? #4</description></variable><variable id="phv00298432.v1"><name>WMRL183</name><description>Location of the #5 RICA plaque</description></variable><variable id="phv00298433.v1"><name>WMRL184</name><description>Is this the most stenotic RICA plaque? #5</description></variable><variable id="phv00298434.v1"><name>WMRL185</name><description>Location of the #6 RICA plaque</description></variable><variable id="phv00298435.v1"><name>WMRL186</name><description>Is this the most stenotic RICA plaque? #6</description></variable><variable id="phv00298436.v1"><name>WMRL187</name><description>Location of the #7 RICA plaque</description></variable><variable id="phv00298437.v1"><name>WMRL188</name><description>Is this the most stenotic RICA plaque? #7</description></variable><variable id="phv00298438.v1"><name>WMRL189</name><description>Location of the #8 RICA plaque</description></variable><variable id="phv00298439.v1"><name>WMRL190</name><description>Is this the most stenotic RICA plaque? #8</description></variable><variable id="phv00298440.v1"><name>WMRL191</name><description>Location of the #9 RICA plaque</description></variable><variable id="phv00298441.v1"><name>WMRL192</name><description>Is this the most stenotic RICA plaque? #9</description></variable><variable id="phv00298442.v1"><name>WMRL193</name><description>Location of the #10 RICA plaque</description></variable><variable id="phv00298443.v1"><name>WMRL194</name><description>Is this the most stenotic RICA plaque? #10</description></variable><variable id="phv00298444.v1"><name>WMRL195</name><description>Confidence factor RICA_plaq</description></variable><variable id="phv00298445.v1"><name>WMRL196</name><description>Identified RICA_plaq</description></variable><variable id="phv00298446.v1"><name>WMRL197</name><description>Calcification RICA_plaq</description></variable><variable id="phv00298447.v1"><name>WMRL198</name><description>T1 Hyperintense RICA_plaq</description></variable><variable id="phv00298448.v1"><name>WMRL199</name><description>Degree of stenosis RICA_plaq</description></variable><variable id="phv00298449.v1"><name>WMRL200</name><description>Number of LICA plaques</description></variable><variable id="phv00298450.v1"><name>WMRL201</name><description>Location of the #1 LICA plaque</description></variable><variable id="phv00298451.v1"><name>WMRL202</name><description>Is this the most stenotic LICA plaque? #1</description></variable><variable id="phv00298452.v1"><name>WMRL203</name><description>Location of the #2 LICA plaque</description></variable><variable id="phv00298453.v1"><name>WMRL204</name><description>Is this the most stenotic LICA plaque? #2</description></variable><variable id="phv00298454.v1"><name>WMRL205</name><description>Location of the #3 LICA plaque</description></variable><variable id="phv00298455.v1"><name>WMRL206</name><description>Is this the most stenotic LICA plaque? #3</description></variable><variable id="phv00298456.v1"><name>WMRL207</name><description>Location of the #4 LICA plaque</description></variable><variable id="phv00298457.v1"><name>WMRL208</name><description>Is this the most stenotic LICA plaque? #4</description></variable><variable id="phv00298458.v1"><name>WMRL209</name><description>Location of the #5 LICA plaque</description></variable><variable id="phv00298459.v1"><name>WMRL210</name><description>Is this the most stenotic LICA plaque? #5</description></variable><variable id="phv00298460.v1"><name>WMRL211</name><description>Location of the #6 LICA plaque</description></variable><variable id="phv00298461.v1"><name>WMRL212</name><description>Is this the most stenotic LICA plaque? #6</description></variable><variable id="phv00298462.v1"><name>WMRL213</name><description>Location of the #7 LICA plaque</description></variable><variable id="phv00298463.v1"><name>WMRL214</name><description>Is this the most stenotic LICA plaque? #7</description></variable><variable id="phv00298464.v1"><name>WMRL215</name><description>Location of the #8 LICA plaque</description></variable><variable id="phv00298465.v1"><name>WMRL216</name><description>Is this the most stenotic LICA plaque? #8</description></variable><variable id="phv00298466.v1"><name>WMRL217</name><description>Location of the #9 LICA plaque</description></variable><variable id="phv00298467.v1"><name>WMRL218</name><description>Is this the most stenotic LICA plaque? #9</description></variable><variable id="phv00298468.v1"><name>WMRL219</name><description>Location of the #10 LICA plaque</description></variable><variable id="phv00298469.v1"><name>WMRL220</name><description>Is this the most stenotic LICA plaque? #10</description></variable><variable id="phv00298470.v1"><name>WMRL221</name><description>Confidence factor LICA_plaq</description></variable><variable id="phv00298471.v1"><name>WMRL222</name><description>Identified LICA_plaq</description></variable><variable id="phv00298472.v1"><name>WMRL223</name><description>Calcification LICA_plaq</description></variable><variable id="phv00298473.v1"><name>WMRL224</name><description>T1 Hyperintense LICA_plaq</description></variable><variable id="phv00298474.v1"><name>WMRL225</name><description>Degree of stenosis LICA_plaq</description></variable><variable id="phv00298475.v1"><name>WMRL226</name><description>Number Of RPCA plaques</description></variable><variable id="phv00298476.v1"><name>WMRL227</name><description>Location of the #1 RPCA plaque</description></variable><variable id="phv00298477.v1"><name>WMRL228</name><description>Is this the most stenotic RPCA plaque? #1</description></variable><variable id="phv00298478.v1"><name>WMRL229</name><description>Location of the #2 RPCA plaque</description></variable><variable id="phv00298479.v1"><name>WMRL230</name><description>Is this the most stenotic RPCA plaque? #2</description></variable><variable id="phv00298480.v1"><name>WMRL231</name><description>Location of the #3 RPCA plaque</description></variable><variable id="phv00298481.v1"><name>WMRL232</name><description>Is this the most stenotic RPCA plaque? #3</description></variable><variable id="phv00298482.v1"><name>WMRL233</name><description>Location of the #4 RPCA plaque</description></variable><variable id="phv00298483.v1"><name>WMRL234</name><description>Is this the most stenotic RPCA plaque? #4</description></variable><variable id="phv00298484.v1"><name>WMRL235</name><description>Location of the #5 RPCA plaque</description></variable><variable id="phv00298485.v1"><name>WMRL236</name><description>Is this the most stenotic RPCA plaque? #5</description></variable><variable id="phv00298486.v1"><name>WMRL237</name><description>Location of the #6 RPCA plaque</description></variable><variable id="phv00298487.v1"><name>WMRL238</name><description>Is this the most stenotic RPCA plaque? #6</description></variable><variable id="phv00298488.v1"><name>WMRL239</name><description>Location of the #7 RPCA plaque</description></variable><variable id="phv00298489.v1"><name>WMRL240</name><description>Is this the most stenotic RPCA plaque? #7</description></variable><variable id="phv00298490.v1"><name>WMRL241</name><description>Location of the #8 RPCA plaque</description></variable><variable id="phv00298491.v1"><name>WMRL242</name><description>Is this the most stenotic RPCA plaque? #8</description></variable><variable id="phv00298492.v1"><name>WMRL243</name><description>Location of the #9 RPCA plaque</description></variable><variable id="phv00298493.v1"><name>WMRL244</name><description>Is this the most stenotic RPCA plaque? #9</description></variable><variable id="phv00298494.v1"><name>WMRL245</name><description>Location of the #10 RPCA plaque</description></variable><variable id="phv00298495.v1"><name>WMRL246</name><description>Is this the most stenotic RPCA plaque? #10</description></variable><variable id="phv00298496.v1"><name>WMRL247</name><description>Confidence factor RPCA_plaq</description></variable><variable id="phv00298497.v1"><name>WMRL248</name><description>Identified RPCA_plaq</description></variable><variable id="phv00298498.v1"><name>WMRL249</name><description>Calcification RPCA_plaq</description></variable><variable id="phv00298499.v1"><name>WMRL250</name><description>T1 Hyperintense RPCA_plaq</description></variable><variable id="phv00298500.v1"><name>WMRL251</name><description>Degree of stenosis RPCA_plaq</description></variable><variable id="phv00298501.v1"><name>WMRL252</name><description>Number of LPCA plaques</description></variable><variable id="phv00298502.v1"><name>WMRL253</name><description>Location of the #1 LPCA plaque</description></variable><variable id="phv00298503.v1"><name>WMRL254</name><description>Is this the most stenotic LPCA plaque? #1</description></variable><variable id="phv00298504.v1"><name>WMRL255</name><description>Location of the #2 LPCA plaque</description></variable><variable id="phv00298505.v1"><name>WMRL256</name><description>Is this the most stenotic LPCA plaque? #2</description></variable><variable id="phv00298506.v1"><name>WMRL257</name><description>Location of the #3 LPCA plaque</description></variable><variable id="phv00298507.v1"><name>WMRL258</name><description>Is this the most stenotic LPCA plaque? #3</description></variable><variable id="phv00298508.v1"><name>WMRL259</name><description>Location of the #4 LPCA plaque</description></variable><variable id="phv00298509.v1"><name>WMRL260</name><description>Is this the most stenotic LPCA plaque? #4</description></variable><variable id="phv00298510.v1"><name>WMRL261</name><description>Location of the #5 LPCA plaque</description></variable><variable id="phv00298511.v1"><name>WMRL262</name><description>Is this the most stenotic LPCA plaque? #5</description></variable><variable id="phv00298512.v1"><name>WMRL263</name><description>Location of the #6 LPCA plaque</description></variable><variable id="phv00298513.v1"><name>WMRL264</name><description>Is this the most stenotic LPCA plaque? #6</description></variable><variable id="phv00298514.v1"><name>WMRL265</name><description>Location of the #7 LPCA plaque</description></variable><variable id="phv00298515.v1"><name>WMRL266</name><description>Is this the most stenotic LPCA plaque? #7</description></variable><variable id="phv00298516.v1"><name>WMRL267</name><description>Location of the #8 LPCA plaque</description></variable><variable id="phv00298517.v1"><name>WMRL268</name><description>Is this the most stenotic LPCA plaque? #8</description></variable><variable id="phv00298518.v1"><name>WMRL269</name><description>Location of the #9 LPCA plaque</description></variable><variable id="phv00298519.v1"><name>WMRL270</name><description>Is this the most stenotic LPCA plaque? #9</description></variable><variable id="phv00298520.v1"><name>WMRL271</name><description>Location of the #10 LPCA plaque</description></variable><variable id="phv00298521.v1"><name>WMRL272</name><description>Is this the most stenotic LPCA plaque? #10</description></variable><variable id="phv00298522.v1"><name>WMRL273</name><description>Confidence factor LPCA_plaq</description></variable><variable id="phv00298523.v1"><name>WMRL274</name><description>Identified LPCA_plaq</description></variable><variable id="phv00298524.v1"><name>WMRL275</name><description>Calcification LPCA_plaq</description></variable><variable id="phv00298525.v1"><name>WMRL276</name><description>T1 Hyperintense LPCA_plaq</description></variable><variable id="phv00298526.v1"><name>WMRL277</name><description>Degree of stenosis LPCA_plaq</description></variable><variable id="phv00298527.v1"><name>WMRL278</name><description>Number of BASILAR plaques</description></variable><variable id="phv00298528.v1"><name>WMRL279</name><description>Location of the #1 BASILAR plaque</description></variable><variable id="phv00298529.v1"><name>WMRL280</name><description>Is this the most stenotic BASILAR plaque? #1</description></variable><variable id="phv00298530.v1"><name>WMRL281</name><description>Location of the #2 BASILAR plaque</description></variable><variable id="phv00298531.v1"><name>WMRL282</name><description>Is this the most stenotic BASILAR plaque? #2</description></variable><variable id="phv00298532.v1"><name>WMRL283</name><description>Location of the #3 BASILAR plaque</description></variable><variable id="phv00298533.v1"><name>WMRL284</name><description>Is this the most stenotic BASILAR plaque? #3</description></variable><variable id="phv00298534.v1"><name>WMRL285</name><description>Location of the #4 BASILAR plaque</description></variable><variable id="phv00298535.v1"><name>WMRL286</name><description>Is this the most stenotic BASILAR plaque? #4</description></variable><variable id="phv00298536.v1"><name>WMRL287</name><description>Location of the #5 BASILAR plaque</description></variable><variable id="phv00298537.v1"><name>WMRL288</name><description>Is this the most stenotic BASILAR plaque? #5</description></variable><variable id="phv00298538.v1"><name>WMRL289</name><description>Location of the #6 BASILAR plaque</description></variable><variable id="phv00298539.v1"><name>WMRL290</name><description>Is this the most stenotic BASILAR plaque? #6</description></variable><variable id="phv00298540.v1"><name>WMRL291</name><description>Location of the #7 BASILAR plaque</description></variable><variable id="phv00298541.v1"><name>WMRL292</name><description>Is this the most stenotic BASILAR plaque? #7</description></variable><variable id="phv00298542.v1"><name>WMRL293</name><description>Location of the #8 BASILAR plaque</description></variable><variable id="phv00298543.v1"><name>WMRL294</name><description>Is this the most stenotic BASILAR plaque? #8</description></variable><variable id="phv00298544.v1"><name>WMRL295</name><description>Location of the #9 BASILAR plaque</description></variable><variable id="phv00298545.v1"><name>WMRL296</name><description>Is this the most stenotic BASILAR plaque? #9</description></variable><variable id="phv00298546.v1"><name>WMRL297</name><description>Location of the #10 BASILAR plaque</description></variable><variable id="phv00298547.v1"><name>WMRL298</name><description>Is this the most stenotic BASILAR plaque? #10</description></variable><variable id="phv00298548.v1"><name>WMRL299</name><description>Confidence factor Basilar_plaq</description></variable><variable id="phv00298549.v1"><name>WMRL300</name><description>Identified Basilar_plaq</description></variable><variable id="phv00298550.v1"><name>WMRL301</name><description>Calcification Basilar_plaq</description></variable><variable id="phv00298551.v1"><name>WMRL302</name><description>T1 Hyperintense Basilar_plaq</description></variable><variable id="phv00298552.v1"><name>WMRL303</name><description>Degree of stenosis Basilar_plaq</description></variable><variable id="phv00298553.v1"><name>WMRL304</name><description>Number of vertebral plaques</description></variable><variable id="phv00298554.v1"><name>WMRL305</name><description>Location of the #1 vertebral plaque</description></variable><variable id="phv00298555.v1"><name>WMRL306</name><description>Is this the most stenotic vertebral plaque? #1</description></variable><variable id="phv00298556.v1"><name>WMRL307</name><description>Location of the #2 vertebral plaque</description></variable><variable id="phv00298557.v1"><name>WMRL308</name><description>Is this the most stenotic vertebral plaque? #2</description></variable><variable id="phv00298558.v1"><name>WMRL309</name><description>Location of the #3 vertebral plaque</description></variable><variable id="phv00298559.v1"><name>WMRL310</name><description>Is this the most stenotic vertebral plaque? #3</description></variable><variable id="phv00298560.v1"><name>WMRL311</name><description>Location of the #4 vertebral plaque</description></variable><variable id="phv00298561.v1"><name>WMRL312</name><description>Is this the most stenotic vertebral plaque? #4</description></variable><variable id="phv00298562.v1"><name>WMRL313</name><description>Location of the #5 vertebral plaque</description></variable><variable id="phv00298563.v1"><name>WMRL314</name><description>Is this the most stenotic vertebral plaque? #5</description></variable><variable id="phv00298564.v1"><name>WMRL315</name><description>Location of the #6 vertebral plaque</description></variable><variable id="phv00298565.v1"><name>WMRL316</name><description>Is this the most stenotic vertebral plaque? #6</description></variable><variable id="phv00298566.v1"><name>WMRL317</name><description>Location of the #7 vertebral plaque</description></variable><variable id="phv00298567.v1"><name>WMRL318</name><description>Is this the most stenotic vertebral plaque? #7</description></variable><variable id="phv00298568.v1"><name>WMRL319</name><description>Location of the #8 vertebral plaque</description></variable><variable id="phv00298569.v1"><name>WMRL320</name><description>Is this the most stenotic vertebral plaque? #8</description></variable><variable id="phv00298570.v1"><name>WMRL321</name><description>Location of the #9 vertebral plaque</description></variable><variable id="phv00298571.v1"><name>WMRL322</name><description>Is this the most stenotic vertebral plaque? #9</description></variable><variable id="phv00298572.v1"><name>WMRL323</name><description>Location of the #10 vertebral plaque</description></variable><variable id="phv00298573.v1"><name>WMRL324</name><description>Is this the most stenotic vertebral plaque? #10</description></variable><variable id="phv00298574.v1"><name>WMRL325</name><description>Confidence factor Vertebral_plaq</description></variable><variable id="phv00298575.v1"><name>WMRL326</name><description>Identified Vertebral_plaq</description></variable><variable id="phv00298576.v1"><name>WMRL327</name><description>Calcification Vertebral_plaq</description></variable><variable id="phv00298577.v1"><name>WMRL328</name><description>T1 Hyperintense Vertebral_plaq</description></variable><variable id="phv00298578.v1"><name>WMRL329</name><description>Degree of stenosis Vertebral_plaq</description></variable><variable id="phv00298579.v1"><name>WMRL330</name><description>Total number of plaques</description></variable><variable id="phv00298580.v1"><name>WMRL331</name><description>TOF adherence</description></variable><variable id="phv00298581.v1"><name>WMRL332</name><description>Space adherence</description></variable><variable id="phv00298582.v1"><name>WMRL333</name><description>Was RM3 included?</description></variable><variable id="phv00298583.v1"><name>WMRL334</name><description>If RM3 excluded, describe the most distal</description></variable><variable id="phv00298584.v1"><name>WMRL335</name><description>Was LM3 included?</description></variable><variable id="phv00298585.v1"><name>WMRL336</name><description>If LM3 excluded, describe the most distal</description></variable><variable id="phv00298586.v1"><name>WMRL337</name><description>Was RP3 included?</description></variable><variable id="phv00298587.v1"><name>WMRL338</name><description>If RP3 excluded, describe the most distal</description></variable><variable id="phv00298588.v1"><name>WMRL339</name><description>Was LP3 included?</description></variable><variable id="phv00298589.v1"><name>WMRL340</name><description>If LP3 excluded, describe the most distal</description></variable><variable id="phv00298590.v1"><name>WMRL341</name><description>Was RV4 included?</description></variable><variable id="phv00298591.v1"><name>WMRL342</name><description>Was LV4 included?</description></variable><variable id="phv00298592.v1"><name>WMRL343</name><description>TOF quality</description></variable><variable id="phv00298593.v1"><name>WMRL344</name><description>Space Quality</description></variable><variable id="phv00298594.v1"><name>WMRL345</name><description>Cavernous calcification</description><unit>Right</unit></variable><variable id="phv00298595.v1"><name>WMRL346</name><description>Cavernous calcification</description><unit>Left</unit></variable><variable id="phv00298596.v1"><name>WMRL349</name><description>Qualitative complete?</description></variable><variable id="phv00298597.v1"><name>WMRL350</name><description>Assigned analyst code</description><unit>Quantitati</unit></variable><variable id="phv00298598.v1"><name>WMRL351</name><description>Is any plaque found in the qualitative analysis?</description></variable><variable id="phv00298599.v1"><name>WMRL352</name><description>Does the quantitative analysis agree with qualitative analysis?</description></variable><variable id="phv00298600.v1"><name>WMRL354</name><description>Is the designated segment  in RMCA measured?</description></variable><variable id="phv00298601.v1"><name>WMRL355</name><description>If RMCA measured and &lt; 6mm, please record the length.</description></variable><variable id="phv00298602.v1"><name>WMRL356</name><description>RMCA wall delineation: lumen</description></variable><variable id="phv00298603.v1"><name>WMRL357</name><description>RMCA wall delineation: wall</description></variable><variable id="phv00298604.v1"><name>WMRL358</name><description>Is plaque present In RMCA?</description></variable><variable id="phv00298605.v1"><name>WMRL359</name><description>Is plaque in RMCA analyzable?</description></variable><variable id="phv00298606.v1"><name>WMRL360</name><description>Plaque in RMCA delineation: lumen</description></variable><variable id="phv00298607.v1"><name>WMRL361</name><description>Plaque in RMCA delineation: wall</description></variable><variable id="phv00298608.v1"><name>WMRL362</name><description>Is the designated segment in lMCA measured?</description></variable><variable id="phv00298609.v1"><name>WMRL363</name><description>If lMCA measured And &lt; 6mm, please record the length.</description></variable><variable id="phv00298610.v1"><name>WMRL364</name><description>LMCA wall delineation: lumen</description></variable><variable id="phv00298611.v1"><name>WMRL365</name><description>LMCA wall delineation: wall</description></variable><variable id="phv00298612.v1"><name>WMRL366</name><description>Is plaque present in lMCA?</description></variable><variable id="phv00298613.v1"><name>WMRL367</name><description>Is plaque in lMCA analyzable?</description></variable><variable id="phv00298614.v1"><name>WMRL368</name><description>Plaque in lMCA delineation: lumen</description></variable><variable id="phv00298615.v1"><name>WMRL369</name><description>Plaque in lMCA delineation: wall</description></variable><variable id="phv00298616.v1"><name>WMRL370</name><description>Is the designated segment in RICA measured?</description></variable><variable id="phv00298617.v1"><name>WMRL371</name><description>If RICA measured and &lt; 6mm, please record the length.</description></variable><variable id="phv00298618.v1"><name>WMRL372</name><description>RICA wall delineation: lumen</description></variable><variable id="phv00298619.v1"><name>WMRL373</name><description>RICA wall delineation: wall</description></variable><variable id="phv00298620.v1"><name>WMRL374</name><description>Is plaque present in RICA?</description></variable><variable id="phv00298621.v1"><name>WMRL375</name><description>Is plaque in RICAA analyzable?</description></variable><variable id="phv00298622.v1"><name>WMRL376</name><description>Plaque in RICA delineation: lumen</description></variable><variable id="phv00298623.v1"><name>WMRL377</name><description>Plaque in RICA delineation: wall</description></variable><variable id="phv00298624.v1"><name>WMRL378</name><description>Is the designated segment in LICA measured?</description></variable><variable id="phv00298625.v1"><name>WMRL379</name><description>If LICA measured And &lt; 6mm, please record the length.</description></variable><variable id="phv00298626.v1"><name>WMRL380</name><description>LICA wall delineation: lumen</description></variable><variable id="phv00298627.v1"><name>WMRL381</name><description>LICA wall delineation: wall</description></variable><variable id="phv00298628.v1"><name>WMRL382</name><description>Is plaque Present In LICA?</description></variable><variable id="phv00298629.v1"><name>WMRL383</name><description>Is plaque In LICA analyzable?</description></variable><variable id="phv00298630.v1"><name>WMRL384</name><description>Plaque In LICA Delineation: lumen</description></variable><variable id="phv00298631.v1"><name>WMRL385</name><description>Plaque In LICA Delineation: wall</description></variable><variable id="phv00298632.v1"><name>WMRL386</name><description>Is the designated segment in basilar-proxy measured?</description></variable><variable id="phv00298633.v1"><name>WMRL387</name><description>If basilar-proxy measured and &lt; 5mm, please record the length.</description></variable><variable id="phv00298634.v1"><name>WMRL388</name><description>Basilar-proxy wall delineation: lumen</description></variable><variable id="phv00298635.v1"><name>WMRL389</name><description>Basilar-proxy all delineation: wall</description></variable><variable id="phv00298636.v1"><name>WMRL390</name><description>Is plaque present in basilar-proximal half?</description></variable><variable id="phv00298637.v1"><name>WMRL391</name><description>Is plaque In basilar-proxy analyzable?</description></variable><variable id="phv00298638.v1"><name>WMRL392</name><description>Plaque In basilar-proxy delineation: lumen</description></variable><variable id="phv00298639.v1"><name>WMRL393</name><description>Plaque In basilar-proxy delineation: wall</description></variable><variable id="phv00298640.v1"><name>WMRL394</name><description>Is the designated segment in basilar-dist measured?</description></variable><variable id="phv00298641.v1"><name>WMRL395</name><description>If basilar-dist measured and &lt; 5mm, please record the length.</description></variable><variable id="phv00298642.v1"><name>WMRL396</name><description>Basilar-dist wall delineation: lumen</description></variable><variable id="phv00298643.v1"><name>WMRL397</name><description>Basilar-dist wall delineation: wall</description></variable><variable id="phv00298644.v1"><name>WMRL398</name><description>Is plaque present in basilar-distal half?</description></variable><variable id="phv00298645.v1"><name>WMRL399</name><description>Is plaque in basilar-dist analyzable?</description></variable><variable id="phv00298646.v1"><name>WMRL400</name><description>Plaque in basilar-dist delineation: lumen</description></variable><variable id="phv00298647.v1"><name>WMRL401</name><description>Plaque in basilar-dist delineation: wall</description></variable><variable id="phv00298648.v1"><name>WMRL402</name><description>Is the designated segment in V4 measured?</description></variable><variable id="phv00298649.v1"><name>WMRL403</name><description>If V4 measured and &lt; 6mm, please record the length.</description></variable><variable id="phv00298650.v1"><name>WMRL404</name><description>V4 wall delineation: lumen</description></variable><variable id="phv00298651.v1"><name>WMRL405</name><description>V4 wall delineation: wall</description></variable><variable id="phv00298652.v1"><name>WMRL406</name><description>Is plaque Present In V4?</description></variable><variable id="phv00298653.v1"><name>WMRL407</name><description>Is plaque In V4 analyzable?</description></variable><variable id="phv00298654.v1"><name>WMRL408</name><description>Plaque in V4 delineation: lumen</description></variable><variable id="phv00298655.v1"><name>WMRL409</name><description>Plaque in V4 delineation: wall</description></variable><variable id="phv00298656.v1"><name>WMRL410</name><description>Is the designated segment in A1 measured?</description></variable><variable id="phv00298657.v1"><name>WMRL411</name><description>If A1 measured and &lt; 6mm, please record the length.</description></variable><variable id="phv00298658.v1"><name>WMRL412</name><description>A1 wall delineation: lumen</description></variable><variable id="phv00298659.v1"><name>WMRL413</name><description>A1 wall delineation: wall</description></variable><variable id="phv00298660.v1"><name>WMRL414</name><description>Is plaque present In A1?</description></variable><variable id="phv00298661.v1"><name>WMRL415</name><description>Is plaque In A1 analyzable?</description></variable><variable id="phv00298662.v1"><name>WMRL416</name><description>Plaque in A1 delineation: lumen</description></variable><variable id="phv00298663.v1"><name>WMRL417</name><description>Plaque in A1 delineation: wall</description></variable><variable id="phv00298664.v1"><name>WMRL418</name><description>Is plaque present in RPCA?</description></variable><variable id="phv00298665.v1"><name>WMRL419</name><description>Is plaque in RPCA analyzable?</description></variable><variable id="phv00298666.v1"><name>WMRL420</name><description>Plaque in RPCA delineation: lumen</description></variable><variable id="phv00298667.v1"><name>WMRL421</name><description>Plaque in RPCA delineation: wall</description></variable><variable id="phv00298668.v1"><name>WMRL422</name><description>Is plaque present in LPCA?</description></variable><variable id="phv00298669.v1"><name>WMRL423</name><description>Is plaque in LPCA analyzable?</description></variable><variable id="phv00298670.v1"><name>WMRL424</name><description>Plaque in LPCA delineation: lumen</description></variable><variable id="phv00298671.v1"><name>WMRL425</name><description>Plaque in LPCA delineation: wall</description></variable><variable id="phv00298672.v1"><name>WMRL427</name><description>Quantitative complete?</description></variable></data_table>
