<?xml-stylesheet type="text/xsl" href="varreports_v3.xsl"?><data_table name="NHX" dataset_id="pht006457.v1" study_name="Atherosclerosis Risk in Communities (ARIC) Cohort" study_id="phs000280.v5" participant_set="1" date_created="2018/11/19"><description>Neurological History Form, Visit 5. Participants with or without atherosclerosis and cardiovascular disease and involved in the "Atherosclerosis Risk in Communities (ARIC) Cohort" project.</description><variable id="phv00297336.v1.p1" var_name="SUBJECT_ID" calculated_type="string" reported_type=""><description>ARIC subject ID [Neurological History Form]</description><total><subject_profile><sex><male>1125</male><female>1408</female></sex></subject_profile><stats><stat n="2537" nulls="0"/></stats></total></variable><variable id="phv00297336.v1.p1.c1" var_name="SUBJECT_ID" calculated_type="string" reported_type=""><description>ARIC subject ID [Neurological History Form]</description><total><subject_profile><sex><male>1121</male><female>1403</female></sex></subject_profile><stats><stat n="2528" nulls="0"/></stats></total></variable><variable id="phv00297336.v1.p1.c2" var_name="SUBJECT_ID" calculated_type="string" reported_type=""><description>ARIC subject ID [Neurological History Form]</description><total><subject_profile><sex><male>4</male><female>5</female></sex></subject_profile><stats><stat n="9" nulls="0"/></stats></total></variable><variable id="phv00297337.v1.p1" var_name="NHX1" calculated_type="enum_integer" reported_type=""><description>Q1. Informed of Parkinson's disease by doctor [Neurological History Form]</description><total><subject_profile><sex><male>1125</male><female>1408</female></sex></subject_profile><stats><stat n="2537" nulls="0" mean_count="845.7" sd="1431" median_count="33" min_count="6" max_count="2498"/><enum code="N" count="2498">No</enum><enum code="Y" count="33">Yes</enum><enum code="D" count="6">Do not know</enum></stats></total></variable><variable id="phv00297337.v1.p1.c1" var_name="NHX1" calculated_type="enum_integer" reported_type=""><description>Q1. Informed of Parkinson's disease by doctor [Neurological History Form]</description><total><subject_profile><sex><male>1121</male><female>1403</female></sex></subject_profile><stats><stat n="2528" nulls="0" mean_count="842.7" sd="1427" median_count="32" min_count="6" max_count="2490"/><enum code="N" count="2490">No</enum><enum code="Y" count="32">Yes</enum><enum code="D" count="6">Do not know</enum></stats></total></variable><variable id="phv00297337.v1.p1.c2" var_name="NHX1" calculated_type="enum_integer" reported_type=""><description>Q1. Informed of Parkinson's disease by doctor [Neurological History Form]</description><total><subject_profile><sex><male>4</male><female>5</female></sex></subject_profile><stats><stat n="9" nulls="0" mean_count="4.5" sd="4.95" median_count="4.5" min_count="1" max_count="8"/><enum code="N" count="8">No</enum><enum code="Y" count="1">Yes</enum></stats></total></variable><variable id="phv00297338.v1.p1" var_name="NHX1A" calculated_type="integer" reported_type=""><description>Q1a. Age When told of Parkinson's disease [Neurological History Form]</description><total><subject_profile><sex><male>20</male><female>11</female></sex></subject_profile><stats><stat n="31" nulls="2506" mean="74.1" sd="6.886" median="75" min="59" max="86"/><example count="3">77</example><example count="3">65</example><example count="3">79</example><example count="3">70</example><example count="3">75</example><example count="2">81</example><example count="2">80</example><example count="1">84</example><example count="1">73</example><example count="1">74</example></stats></total></variable><variable id="phv00297338.v1.p1.c1" var_name="NHX1A" calculated_type="integer" reported_type=""><description>Q1a. Age When told of Parkinson's disease [Neurological History Form]</description><total><subject_profile><sex><male>19</male><female>11</female></sex></subject_profile><stats><stat n="30" nulls="2498" mean="74.23" sd="6.961" median="75" min="59" max="86"/><example count="3">77</example><example count="3">65</example><example count="3">79</example><example count="3">75</example><example count="2">81</example><example count="2">80</example><example count="2">70</example><example count="1">84</example><example count="1">73</example><example count="1">74</example></stats></total></variable><variable id="phv00297338.v1.p1.c2" var_name="NHX1A" calculated_type="integer" reported_type=""><description>Q1a. Age When told of Parkinson's disease [Neurological History Form]</description><total><subject_profile><sex><male>1</male></sex></subject_profile><stats><stat n="1" nulls="8" mean="70" median="70" min="70" max="70"/><enum count="1">70</enum></stats></total></variable><variable id="phv00297339.v1.p1" var_name="NHX2" calculated_type="enum_integer" reported_type=""><description>Q2. Loss of consciousness due to head injury [Neurological History Form]</description><total><subject_profile><sex><male>1125</male><female>1408</female></sex></subject_profile><stats><stat n="2537" nulls="0" mean_count="845.7" sd="1112" median_count="380" min_count="42" max_count="2115"/><enum code="N" count="2115">No</enum><enum code="Y" count="380">Yes</enum><enum code="D" count="42">Do not know</enum></stats></total></variable><variable id="phv00297339.v1.p1.c1" var_name="NHX2" calculated_type="enum_integer" reported_type=""><description>Q2. Loss of consciousness due to head injury [Neurological History Form]</description><total><subject_profile><sex><male>1121</male><female>1403</female></sex></subject_profile><stats><stat n="2528" nulls="0" mean_count="842.7" sd="1108" median_count="379" min_count="42" max_count="2107"/><enum code="N" count="2107">No</enum><enum code="Y" count="379">Yes</enum><enum code="D" count="42">Do not know</enum></stats></total></variable><variable id="phv00297339.v1.p1.c2" var_name="NHX2" calculated_type="enum_integer" reported_type=""><description>Q2. Loss of consciousness due to head injury [Neurological History Form]</description><total><subject_profile><sex><male>4</male><female>5</female></sex></subject_profile><stats><stat n="9" nulls="0" mean_count="4.5" sd="4.95" median_count="4.5" min_count="1" max_count="8"/><enum code="N" count="8">No</enum><enum code="Y" count="1">Yes</enum></stats></total></variable><variable id="phv00297340.v1.p1" var_name="NHX2A" calculated_type="enum_integer" units="&gt;5 Min" reported_type=""><description>Q2a. Extended loss of consciousness due to head injury [Neurological History Form]</description><total><subject_profile><sex><male>249</male><female>125</female></sex></subject_profile><stats><stat n="374" nulls="2163" mean_count="124.7" sd="50.2" median_count="115" min_count="80" max_count="179"/><enum code="N" count="179">No</enum><enum code="Y" count="115">Yes</enum><enum code="D" count="80">Do not know</enum></stats></total></variable><variable id="phv00297340.v1.p1.c1" var_name="NHX2A" calculated_type="enum_integer" units="&gt;5 Min" reported_type=""><description>Q2a. Extended loss of consciousness due to head injury [Neurological History Form]</description><total><subject_profile><sex><male>248</male><female>125</female></sex></subject_profile><stats><stat n="373" nulls="2155" mean_count="124.3" sd="50.3" median_count="114" min_count="80" max_count="179"/><enum code="N" count="179">No</enum><enum code="Y" count="114">Yes</enum><enum code="D" count="80">Do not know</enum></stats></total></variable><variable id="phv00297340.v1.p1.c2" var_name="NHX2A" calculated_type="enum_integer" units="&gt;5 Min" reported_type=""><description>Q2a. Extended loss of consciousness due to head injury [Neurological History Form]</description><total><subject_profile><sex><male>1</male></sex></subject_profile><stats><stat n="1" nulls="8"/><enum code="Y" count="1">Yes</enum></stats></total></variable><variable id="phv00297341.v1.p1" var_name="NHX2B" calculated_type="enum_integer" reported_type=""><description>Q2b. Long-term problems/dysfunction due to head injury [Neurological History Form]</description><total><subject_profile><sex><male>253</male><female>127</female></sex></subject_profile><stats><stat n="380" nulls="2157" mean_count="126.7" sd="181.6" median_count="32" min_count="12" max_count="336"/><enum code="N" count="336">No</enum><enum code="Y" count="32">Yes</enum><enum code="D" count="12">Do not know</enum></stats></total></variable><variable id="phv00297341.v1.p1.c1" var_name="NHX2B" calculated_type="enum_integer" reported_type=""><description>Q2b. Long-term problems/dysfunction due to head injury [Neurological History Form]</description><total><subject_profile><sex><male>252</male><female>127</female></sex></subject_profile><stats><stat n="379" nulls="2149" mean_count="126.3" sd="181" median_count="32" min_count="12" max_count="335"/><enum code="N" count="335">No</enum><enum code="Y" count="32">Yes</enum><enum code="D" count="12">Do not know</enum></stats></total></variable><variable id="phv00297341.v1.p1.c2" var_name="NHX2B" calculated_type="enum_integer" reported_type=""><description>Q2b. Long-term problems/dysfunction due to head injury [Neurological History Form]</description><total><subject_profile><sex><male>1</male></sex></subject_profile><stats><stat n="1" nulls="8"/><enum code="N" count="1">No</enum></stats></total></variable><variable id="phv00297342.v1.p1" var_name="NHX3" calculated_type="enum_integer" reported_type=""><description>Q3. Have you had a seizure or convulsion? [Neurological History Form]</description><total><subject_profile><sex><male>1125</male><female>1408</female></sex></subject_profile><stats><stat n="2537" nulls="0" mean_count="845.7" sd="1379" median_count="82" min_count="18" max_count="2437"/><enum code="N" count="2437">No</enum><enum code="Y" count="82">Yes</enum><enum code="D" count="18">Do not know</enum></stats></total></variable><variable id="phv00297342.v1.p1.c1" var_name="NHX3" calculated_type="enum_integer" reported_type=""><description>Q3. Have you had a seizure or convulsion? [Neurological History Form]</description><total><subject_profile><sex><male>1121</male><female>1403</female></sex></subject_profile><stats><stat n="2528" nulls="0" mean_count="842.7" sd="1373" median_count="82" min_count="18" max_count="2428"/><enum code="N" count="2428">No</enum><enum code="Y" count="82">Yes</enum><enum code="D" count="18">Do not know</enum></stats></total></variable><variable id="phv00297342.v1.p1.c2" var_name="NHX3" calculated_type="enum_integer" reported_type=""><description>Q3. Have you had a seizure or convulsion? [Neurological History Form]</description><total><subject_profile><sex><male>4</male><female>5</female></sex></subject_profile><stats><stat n="9" nulls="0" mean_count="9" median_count="9" min_count="9" max_count="9"/><enum code="N" count="9">No</enum></stats></total></variable><variable id="phv00297343.v1.p1" var_name="NHX3A" calculated_type="integer" reported_type=""><description>Q3a. Number of seizures or convulsions [Neurological History Form]</description><total><subject_profile><sex><male>30</male><female>36</female></sex></subject_profile><stats><stat n="67" nulls="2470" mean="3.731" sd="9.036" median="1" min="1" max="56"/><enum count="43">1</enum><enum count="7">3</enum><enum count="6">2</enum><enum count="3">5</enum><enum count="3">10</enum><enum count="1">8</enum><enum count="1">6</enum><enum count="1">50</enum><enum count="1">56</enum><enum count="1">9</enum></stats></total></variable><variable id="phv00297343.v1.p1.c1" var_name="NHX3A" calculated_type="integer" reported_type=""><description>Q3a. Number of seizures or convulsions [Neurological History Form]</description><total><subject_profile><sex><male>30</male><female>36</female></sex></subject_profile><stats><stat n="67" nulls="2461" mean="3.731" sd="9.036" median="1" min="1" max="56"/><enum count="43">1</enum><enum count="7">3</enum><enum count="6">2</enum><enum count="3">5</enum><enum count="3">10</enum><enum count="1">8</enum><enum count="1">6</enum><enum count="1">50</enum><enum count="1">56</enum><enum count="1">9</enum></stats></total></variable><variable id="phv00297343.v1.p1.c2" var_name="NHX3A" calculated_type="integer" reported_type=""><description>Q3a. Number of seizures or convulsions [Neurological History Form]</description><total><stats><stat n="0" nulls="9"/></stats></total></variable><variable id="phv00297344.v1.p1" var_name="NHX3B" calculated_type="integer" units="Years" reported_type=""><description>Q3b. Age when first seizure occurred [Neurological History Form]</description><total><subject_profile><sex><male>33</male><female>39</female></sex></subject_profile><stats><stat n="72" nulls="2465" mean="39.18" sd="28" median="33.5" min="1" max="84"/><example count="5">1</example><example count="5">70</example><example count="4">50</example><example count="3">15</example><example count="3">13</example><example count="2">16</example><example count="2">73</example><example count="2">14</example><example count="2">12</example><example count="2">68</example></stats></total></variable><variable id="phv00297344.v1.p1.c1" var_name="NHX3B" calculated_type="integer" units="Years" reported_type=""><description>Q3b. Age when first seizure occurred [Neurological History Form]</description><total><subject_profile><sex><male>33</male><female>39</female></sex></subject_profile><stats><stat n="72" nulls="2456" mean="39.18" sd="28" median="33.5" min="1" max="84"/><example count="5">1</example><example count="5">70</example><example count="4">50</example><example count="3">15</example><example count="3">13</example><example count="2">16</example><example count="2">73</example><example count="2">14</example><example count="2">12</example><example count="2">68</example></stats></total></variable><variable id="phv00297344.v1.p1.c2" var_name="NHX3B" calculated_type="integer" units="Years" reported_type=""><description>Q3b. Age when first seizure occurred [Neurological History Form]</description><total><stats><stat n="0" nulls="9"/></stats></total></variable><variable id="phv00297345.v1.p1" var_name="NHX3C" calculated_type="integer" units="Years" reported_type=""><description>Q3c. Age when last seizure occurred [Neurological History Form]</description><total><subject_profile><sex><male>18</male><female>17</female></sex></subject_profile><stats><stat n="35" nulls="2502" mean="50.23" sd="28.21" median="56" min="6" max="88"/><example count="3">80</example><example count="3">50</example><example count="2">23</example><example count="2">61</example><example count="2">6</example><example count="2">82</example><example count="2">79</example><example count="2">7</example><example count="1">71</example><example count="1">55</example></stats></total></variable><variable id="phv00297345.v1.p1.c1" var_name="NHX3C" calculated_type="integer" units="Years" reported_type=""><description>Q3c. Age when last seizure occurred [Neurological History Form]</description><total><subject_profile><sex><male>18</male><female>17</female></sex></subject_profile><stats><stat n="35" nulls="2493" mean="50.23" sd="28.21" median="56" min="6" max="88"/><example count="3">80</example><example count="3">50</example><example count="2">23</example><example count="2">61</example><example count="2">6</example><example count="2">82</example><example count="2">79</example><example count="2">7</example><example count="1">71</example><example count="1">55</example></stats></total></variable><variable id="phv00297345.v1.p1.c2" var_name="NHX3C" calculated_type="integer" units="Years" reported_type=""><description>Q3c. Age when last seizure occurred [Neurological History Form]</description><total><stats><stat n="0" nulls="9"/></stats></total></variable><variable id="phv00297346.v1.p1" var_name="NHX3D" calculated_type="enum_integer" reported_type=""><description>Q3d. Treated with anti-seizure medications [Neurological History Form]</description><total><subject_profile><sex><male>37</male><female>43</female></sex></subject_profile><stats><stat n="81" nulls="2456" mean_count="27" sd="19.97" median_count="37" min_count="4" max_count="40"/><enum code="N" count="40">No</enum><enum code="Y" count="37">Yes</enum><enum code="D" count="4">Do not know</enum></stats></total></variable><variable id="phv00297346.v1.p1.c1" var_name="NHX3D" calculated_type="enum_integer" reported_type=""><description>Q3d. Treated with anti-seizure medications [Neurological History Form]</description><total><subject_profile><sex><male>37</male><female>43</female></sex></subject_profile><stats><stat n="81" nulls="2447" mean_count="27" sd="19.97" median_count="37" min_count="4" max_count="40"/><enum code="N" count="40">No</enum><enum code="Y" count="37">Yes</enum><enum code="D" count="4">Do not know</enum></stats></total></variable><variable id="phv00297346.v1.p1.c2" var_name="NHX3D" calculated_type="enum_integer" reported_type=""><description>Q3d. Treated with anti-seizure medications [Neurological History Form]</description><total><stats><stat n="0" nulls="9"/></stats></total></variable><variable id="phv00297347.v1.p1" var_name="NHX3E" calculated_type="integer" units="Years" reported_type=""><description>Q3e. Age when started anti-seizure medications [Neurological History Form]</description><total><subject_profile><sex><male>17</male><female>19</female></sex></subject_profile><stats><stat n="36" nulls="2501" mean="53.89" sd="23.91" median="60.5" min="2" max="86"/><example count="3">70</example><example count="3">30</example><example count="2">16</example><example count="2">73</example><example count="2">60</example><example count="2">50</example><example count="1">84</example><example count="1">35</example><example count="1">15</example><example count="1">76</example></stats></total></variable><variable id="phv00297347.v1.p1.c1" var_name="NHX3E" calculated_type="integer" units="Years" reported_type=""><description>Q3e. Age when started anti-seizure medications [Neurological History Form]</description><total><subject_profile><sex><male>17</male><female>19</female></sex></subject_profile><stats><stat n="36" nulls="2492" mean="53.89" sd="23.91" median="60.5" min="2" max="86"/><example count="3">70</example><example count="3">30</example><example count="2">16</example><example count="2">73</example><example count="2">60</example><example count="2">50</example><example count="1">84</example><example count="1">35</example><example count="1">15</example><example count="1">76</example></stats></total></variable><variable id="phv00297347.v1.p1.c2" var_name="NHX3E" calculated_type="integer" units="Years" reported_type=""><description>Q3e. Age when started anti-seizure medications [Neurological History Form]</description><total><stats><stat n="0" nulls="9"/></stats></total></variable><variable id="phv00297348.v1.p1" var_name="NHX4" calculated_type="enum_integer" units="Ms, Brain" reported_type=""><description>Q4. Informed of other neuro disorders by doctor [Neurological History Form]</description><total><subject_profile><sex><male>1124</male><female>1408</female></sex></subject_profile><stats><stat n="2536" nulls="1" mean_count="845.3" sd="1205" median_count="301" min_count="9" max_count="2226"/><enum code="N" count="2226">No</enum><enum code="Y" count="301">Yes</enum><enum code="D" count="9">Do not know</enum></stats></total></variable><variable id="phv00297348.v1.p1.c1" var_name="NHX4" calculated_type="enum_integer" units="Ms, Brain" reported_type=""><description>Q4. Informed of other neuro disorders by doctor [Neurological History Form]</description><total><subject_profile><sex><male>1120</male><female>1403</female></sex></subject_profile><stats><stat n="2527" nulls="1" mean_count="842.3" sd="1199" median_count="301" min_count="9" max_count="2217"/><enum code="N" count="2217">No</enum><enum code="Y" count="301">Yes</enum><enum code="D" count="9">Do not know</enum></stats></total></variable><variable id="phv00297348.v1.p1.c2" var_name="NHX4" calculated_type="enum_integer" units="Ms, Brain" reported_type=""><description>Q4. Informed of other neuro disorders by doctor [Neurological History Form]</description><total><subject_profile><sex><male>4</male><female>5</female></sex></subject_profile><stats><stat n="9" nulls="0" mean_count="9" median_count="9" min_count="9" max_count="9"/><enum code="N" count="9">No</enum></stats></total></variable><variable id="phv00297349.v1.p1" var_name="NHX4A" calculated_type="enum_integer" reported_type=""><description>Q4a. Multiple Sclerosis [Neurological History Form]</description><total><subject_profile><sex><male>140</male><female>158</female></sex></subject_profile><stats><stat n="300" nulls="2237" mean_count="150" sd="209.3" median_count="150" min_count="2" max_count="298"/><enum code="N" count="298">No</enum><enum code="Y" count="2">Yes</enum></stats></total></variable><variable id="phv00297349.v1.p1.c1" var_name="NHX4A" calculated_type="enum_integer" reported_type=""><description>Q4a. Multiple Sclerosis [Neurological History Form]</description><total><subject_profile><sex><male>140</male><female>158</female></sex></subject_profile><stats><stat n="300" nulls="2228" mean_count="150" sd="209.3" median_count="150" min_count="2" max_count="298"/><enum code="N" count="298">No</enum><enum code="Y" count="2">Yes</enum></stats></total></variable><variable id="phv00297349.v1.p1.c2" var_name="NHX4A" calculated_type="enum_integer" reported_type=""><description>Q4a. Multiple Sclerosis [Neurological History Form]</description><total><stats><stat n="0" nulls="9"/></stats></total></variable><variable id="phv00297350.v1.p1" var_name="NHX4A1" calculated_type="integer" units="Years" reported_type=""><description>Q4a1. Multiple sclerosis age at diagnosis [Neurological History Form]</description><total><subject_profile><sex><female>2</female></sex></subject_profile><stats><stat n="2" nulls="2535" mean="38" sd="16.97" median="38" min="26" max="50"/><enum count="1">26</enum><enum count="1">50</enum></stats></total></variable><variable id="phv00297350.v1.p1.c1" var_name="NHX4A1" calculated_type="integer" units="Years" reported_type=""><description>Q4a1. Multiple sclerosis age at diagnosis [Neurological History Form]</description><total><subject_profile><sex><female>2</female></sex></subject_profile><stats><stat n="2" nulls="2526" mean="38" sd="16.97" median="38" min="26" max="50"/><enum count="1">26</enum><enum count="1">50</enum></stats></total></variable><variable id="phv00297350.v1.p1.c2" var_name="NHX4A1" calculated_type="integer" units="Years" reported_type=""><description>Q4a1. Multiple sclerosis age at diagnosis [Neurological History Form]</description><total><stats><stat n="0" nulls="9"/></stats></total></variable><variable id="phv00297351.v1.p1" var_name="NHX4B" calculated_type="enum_integer" reported_type=""><description>Q4b. Brain tumor [Neurological History Form]</description><total><subject_profile><sex><male>140</male><female>158</female></sex></subject_profile><stats><stat n="300" nulls="2237" mean_count="150" sd="181" median_count="150" min_count="22" max_count="278"/><enum code="N" count="278">No</enum><enum code="Y" count="22">Yes</enum></stats></total></variable><variable id="phv00297351.v1.p1.c1" var_name="NHX4B" calculated_type="enum_integer" reported_type=""><description>Q4b. Brain tumor [Neurological History Form]</description><total><subject_profile><sex><male>140</male><female>158</female></sex></subject_profile><stats><stat n="300" nulls="2228" mean_count="150" sd="181" median_count="150" min_count="22" max_count="278"/><enum code="N" count="278">No</enum><enum code="Y" count="22">Yes</enum></stats></total></variable><variable id="phv00297351.v1.p1.c2" var_name="NHX4B" calculated_type="enum_integer" reported_type=""><description>Q4b. Brain tumor [Neurological History Form]</description><total><stats><stat n="0" nulls="9"/></stats></total></variable><variable id="phv00297352.v1.p1" var_name="NHX4B1" calculated_type="integer" units="Years" reported_type=""><description>Q4b1. Brain tumor age at diagnosis [Neurological History Form]</description><total><subject_profile><sex><male>12</male><female>8</female></sex></subject_profile><stats><stat n="20" nulls="2517" mean="61.1" sd="15.06" median="66" min="29" max="83"/><example count="3">70</example><example count="2">68</example><example count="2">40</example><example count="1">57</example><example count="1">29</example><example count="1">62</example><example count="1">67</example><example count="1">74</example><example count="1">77</example><example count="1">83</example></stats></total></variable><variable id="phv00297352.v1.p1.c1" var_name="NHX4B1" calculated_type="integer" units="Years" reported_type=""><description>Q4b1. Brain tumor age at diagnosis [Neurological History Form]</description><total><subject_profile><sex><male>12</male><female>8</female></sex></subject_profile><stats><stat n="20" nulls="2508" mean="61.1" sd="15.06" median="66" min="29" max="83"/><example count="3">70</example><example count="2">68</example><example count="2">40</example><example count="1">57</example><example count="1">29</example><example count="1">62</example><example count="1">67</example><example count="1">74</example><example count="1">77</example><example count="1">83</example></stats></total></variable><variable id="phv00297352.v1.p1.c2" var_name="NHX4B1" calculated_type="integer" units="Years" reported_type=""><description>Q4b1. Brain tumor age at diagnosis [Neurological History Form]</description><total><stats><stat n="0" nulls="9"/></stats></total></variable><variable id="phv00297353.v1.p1" var_name="NHX4C" calculated_type="enum_integer" reported_type=""><description>Q4c. Dementia, Alzheimer's, senility, or hardening of brain's arteries [Neurological History Form]</description><total><subject_profile><sex><male>139</male><female>157</female></sex></subject_profile><stats><stat n="298" nulls="2239" mean_count="149" sd="120.2" median_count="149" min_count="64" max_count="234"/><enum code="N" count="234">No</enum><enum code="Y" count="64">Yes</enum></stats></total></variable><variable id="phv00297353.v1.p1.c1" var_name="NHX4C" calculated_type="enum_integer" reported_type=""><description>Q4c. Dementia, Alzheimer's, senility, or hardening of brain's arteries [Neurological History Form]</description><total><subject_profile><sex><male>139</male><female>157</female></sex></subject_profile><stats><stat n="298" nulls="2230" mean_count="149" sd="120.2" median_count="149" min_count="64" max_count="234"/><enum code="N" count="234">No</enum><enum code="Y" count="64">Yes</enum></stats></total></variable><variable id="phv00297353.v1.p1.c2" var_name="NHX4C" calculated_type="enum_integer" reported_type=""><description>Q4c. Dementia, Alzheimer's, senility, or hardening of brain's arteries [Neurological History Form]</description><total><stats><stat n="0" nulls="9"/></stats></total></variable><variable id="phv00297354.v1.p1" var_name="NHX4C1" calculated_type="integer" units="Years" reported_type=""><description>Q4c1. Dementia age at diagnosis [Neurological History Form]</description><total><subject_profile><sex><male>16</male><female>43</female></sex></subject_profile><stats><stat n="59" nulls="2478" mean="74.64" sd="14.29" median="77" min="1" max="87"/><example count="10">70</example><example count="7">82</example><example count="4">76</example><example count="4">77</example><example count="4">80</example><example count="3">84</example><example count="3">79</example><example count="3">85</example><example count="2">71</example><example count="2">73</example></stats></total></variable><variable id="phv00297354.v1.p1.c1" var_name="NHX4C1" calculated_type="integer" units="Years" reported_type=""><description>Q4c1. Dementia age at diagnosis [Neurological History Form]</description><total><subject_profile><sex><male>16</male><female>43</female></sex></subject_profile><stats><stat n="59" nulls="2469" mean="74.64" sd="14.29" median="77" min="1" max="87"/><example count="10">70</example><example count="7">82</example><example count="4">76</example><example count="4">77</example><example count="4">80</example><example count="3">84</example><example count="3">79</example><example count="3">85</example><example count="2">71</example><example count="2">73</example></stats></total></variable><variable id="phv00297354.v1.p1.c2" var_name="NHX4C1" calculated_type="integer" units="Years" reported_type=""><description>Q4c1. Dementia age at diagnosis [Neurological History Form]</description><total><stats><stat n="0" nulls="9"/></stats></total></variable><variable id="phv00297355.v1.p1" var_name="NHX5" calculated_type="enum_integer" reported_type=""><description>Q5. Surgery or radiation therapy of skull or brain [Neurological History Form]</description><total><subject_profile><sex><male>1125</male><female>1408</female></sex></subject_profile><stats><stat n="2537" nulls="0" mean_count="845.7" sd="1399" median_count="69" min_count="7" max_count="2461"/><enum code="N" count="2461">No</enum><enum code="Y" count="69">Yes</enum><enum code="D" count="7">Do not know</enum></stats></total></variable><variable id="phv00297355.v1.p1.c1" var_name="NHX5" calculated_type="enum_integer" reported_type=""><description>Q5. Surgery or radiation therapy of skull or brain [Neurological History Form]</description><total><subject_profile><sex><male>1121</male><female>1403</female></sex></subject_profile><stats><stat n="2528" nulls="0" mean_count="842.7" sd="1395" median_count="68" min_count="7" max_count="2453"/><enum code="N" count="2453">No</enum><enum code="Y" count="68">Yes</enum><enum code="D" count="7">Do not know</enum></stats></total></variable><variable id="phv00297355.v1.p1.c2" var_name="NHX5" calculated_type="enum_integer" reported_type=""><description>Q5. Surgery or radiation therapy of skull or brain [Neurological History Form]</description><total><subject_profile><sex><male>4</male><female>5</female></sex></subject_profile><stats><stat n="9" nulls="0" mean_count="4.5" sd="4.95" median_count="4.5" min_count="1" max_count="8"/><enum code="N" count="8">No</enum><enum code="Y" count="1">Yes</enum></stats></total></variable><variable id="phv00297356.v1.p1" var_name="NHX5A" calculated_type="enum_integer" reported_type=""><description>Q5a. Surgery involving skull or brain [Neurological History Form]</description><total><subject_profile><sex><male>41</male><female>27</female></sex></subject_profile><stats><stat n="68" nulls="2469" mean_count="22.67" sd="32.47" median_count="7" min_count="1" max_count="60"/><enum code="Y" count="60">Yes</enum><enum code="N" count="7">No</enum><enum code="D" count="1">Do not know</enum></stats></total></variable><variable id="phv00297356.v1.p1.c1" var_name="NHX5A" calculated_type="enum_integer" reported_type=""><description>Q5a. Surgery involving skull or brain [Neurological History Form]</description><total><subject_profile><sex><male>40</male><female>27</female></sex></subject_profile><stats><stat n="67" nulls="2461" mean_count="22.33" sd="31.9" median_count="7" min_count="1" max_count="59"/><enum code="Y" count="59">Yes</enum><enum code="N" count="7">No</enum><enum code="D" count="1">Do not know</enum></stats></total></variable><variable id="phv00297356.v1.p1.c2" var_name="NHX5A" calculated_type="enum_integer" reported_type=""><description>Q5a. Surgery involving skull or brain [Neurological History Form]</description><total><subject_profile><sex><male>1</male></sex></subject_profile><stats><stat n="1" nulls="8"/><enum code="Y" count="1">Yes</enum></stats></total></variable><variable id="phv00297357.v1.p1" var_name="NHX5B" calculated_type="enum_integer" reported_type=""><description>Q5b. Radiation involving skull or brain [Neurological History Form]</description><total><subject_profile><sex><male>41</male><female>27</female></sex></subject_profile><stats><stat n="68" nulls="2469" mean_count="22.67" sd="26.35" median_count="15" min_count="1" max_count="52"/><enum code="N" count="52">No</enum><enum code="Y" count="15">Yes</enum><enum code="D" count="1">Do not know</enum></stats></total></variable><variable id="phv00297357.v1.p1.c1" var_name="NHX5B" calculated_type="enum_integer" reported_type=""><description>Q5b. Radiation involving skull or brain [Neurological History Form]</description><total><subject_profile><sex><male>40</male><female>27</female></sex></subject_profile><stats><stat n="67" nulls="2461" mean_count="22.33" sd="25.79" median_count="15" min_count="1" max_count="51"/><enum code="N" count="51">No</enum><enum code="Y" count="15">Yes</enum><enum code="D" count="1">Do not know</enum></stats></total></variable><variable id="phv00297357.v1.p1.c2" var_name="NHX5B" calculated_type="enum_integer" reported_type=""><description>Q5b. Radiation involving skull or brain [Neurological History Form]</description><total><subject_profile><sex><male>1</male></sex></subject_profile><stats><stat n="1" nulls="8"/><enum code="N" count="1">No</enum></stats></total></variable><variable id="phv00297358.v1.p1" var_name="NHX6" calculated_type="enum_integer" units="Ever" reported_type=""><description>Q6. Depression diagnosis [Neurological History Form]</description><total><subject_profile><sex><male>1124</male><female>1408</female></sex></subject_profile><stats><stat n="2536" nulls="1" mean_count="845.3" sd="1148" median_count="371" min_count="11" max_count="2154"/><enum code="N" count="2154">No</enum><enum code="Y" count="371">Yes</enum><enum code="D" count="11">Do not know</enum></stats></total></variable><variable id="phv00297358.v1.p1.c1" var_name="NHX6" calculated_type="enum_integer" units="Ever" reported_type=""><description>Q6. Depression diagnosis [Neurological History Form]</description><total><subject_profile><sex><male>1120</male><female>1403</female></sex></subject_profile><stats><stat n="2527" nulls="1" mean_count="842.3" sd="1143" median_count="371" min_count="10" max_count="2146"/><enum code="N" count="2146">No</enum><enum code="Y" count="371">Yes</enum><enum code="D" count="10">Do not know</enum></stats></total></variable><variable id="phv00297358.v1.p1.c2" var_name="NHX6" calculated_type="enum_integer" units="Ever" reported_type=""><description>Q6. Depression diagnosis [Neurological History Form]</description><total><subject_profile><sex><male>4</male><female>5</female></sex></subject_profile><stats><stat n="9" nulls="0" mean_count="4.5" sd="4.95" median_count="4.5" min_count="1" max_count="8"/><enum code="N" count="8">No</enum><enum code="D" count="1">Do not know</enum></stats></total></variable><variable id="phv00297359.v1.p1" var_name="NHX6A" calculated_type="enum_integer" units="Past 2 Yrs" reported_type=""><description>A6a. Depression diagnosis [Neurological History Form]</description><total><subject_profile><sex><male>108</male><female>262</female></sex></subject_profile><stats><stat n="371" nulls="2166" mean_count="185.5" sd="37.48" median_count="185.5" min_count="159" max_count="212"/><enum code="N" count="212">No</enum><enum code="Y" count="159">Yes</enum></stats></total></variable><variable id="phv00297359.v1.p1.c1" var_name="NHX6A" calculated_type="enum_integer" units="Past 2 Yrs" reported_type=""><description>A6a. Depression diagnosis [Neurological History Form]</description><total><subject_profile><sex><male>108</male><female>262</female></sex></subject_profile><stats><stat n="371" nulls="2157" mean_count="185.5" sd="37.48" median_count="185.5" min_count="159" max_count="212"/><enum code="N" count="212">No</enum><enum code="Y" count="159">Yes</enum></stats></total></variable><variable id="phv00297359.v1.p1.c2" var_name="NHX6A" calculated_type="enum_integer" units="Past 2 Yrs" reported_type=""><description>A6a. Depression diagnosis [Neurological History Form]</description><total><stats><stat n="0" nulls="9"/></stats></total></variable><variable id="phv00297360.v1.p1" var_name="NHX6B" calculated_type="enum_integer" units="Prior To 2" reported_type=""><description>Q6b. Depression diagnosis [Neurological History Form]</description><total><subject_profile><sex><male>108</male><female>262</female></sex></subject_profile><stats><stat n="371" nulls="2166" mean_count="123.7" sd="156.1" median_count="68" min_count="3" max_count="300"/><enum code="Y" count="300">Yes</enum><enum code="N" count="68">No</enum><enum code="D" count="3">Do not know</enum></stats></total></variable><variable id="phv00297360.v1.p1.c1" var_name="NHX6B" calculated_type="enum_integer" units="Prior To 2" reported_type=""><description>Q6b. Depression diagnosis [Neurological History Form]</description><total><subject_profile><sex><male>108</male><female>262</female></sex></subject_profile><stats><stat n="371" nulls="2157" mean_count="123.7" sd="156.1" median_count="68" min_count="3" max_count="300"/><enum code="Y" count="300">Yes</enum><enum code="N" count="68">No</enum><enum code="D" count="3">Do not know</enum></stats></total></variable><variable id="phv00297360.v1.p1.c2" var_name="NHX6B" calculated_type="enum_integer" units="Prior To 2" reported_type=""><description>Q6b. Depression diagnosis [Neurological History Form]</description><total><stats><stat n="0" nulls="9"/></stats></total></variable><variable id="phv00297361.v1.p1" var_name="NHX6C" calculated_type="enum_integer" reported_type=""><description>Q6c. Treatment for depression [Neurological History Form]</description><total><subject_profile><sex><male>108</male><female>262</female></sex></subject_profile><stats><stat n="371" nulls="2166" mean_count="185.5" sd="227" median_count="185.5" min_count="25" max_count="346"/><enum code="Y" count="346">Yes</enum><enum code="N" count="25">No</enum></stats></total></variable><variable id="phv00297361.v1.p1.c1" var_name="NHX6C" calculated_type="enum_integer" reported_type=""><description>Q6c. Treatment for depression [Neurological History Form]</description><total><subject_profile><sex><male>108</male><female>262</female></sex></subject_profile><stats><stat n="371" nulls="2157" mean_count="185.5" sd="227" median_count="185.5" min_count="25" max_count="346"/><enum code="Y" count="346">Yes</enum><enum code="N" count="25">No</enum></stats></total></variable><variable id="phv00297361.v1.p1.c2" var_name="NHX6C" calculated_type="enum_integer" reported_type=""><description>Q6c. Treatment for depression [Neurological History Form]</description><total><stats><stat n="0" nulls="9"/></stats></total></variable><variable id="phv00297362.v1.p1" var_name="NHX7" calculated_type="enum_integer" reported_type=""><description>Q7. Memory problems [Neurological History Form]</description><total><subject_profile><sex><male>1124</male><female>1404</female></sex></subject_profile><stats><stat n="2532" nulls="5" mean_count="844" sd="774.3" median_count="953" min_count="21" max_count="1558"/><enum code="N" count="1558">No</enum><enum code="Y" count="953">Yes</enum><enum code="D" count="21">Do not know</enum></stats></total></variable><variable id="phv00297362.v1.p1.c1" var_name="NHX7" calculated_type="enum_integer" reported_type=""><description>Q7. Memory problems [Neurological History Form]</description><total><subject_profile><sex><male>1120</male><female>1399</female></sex></subject_profile><stats><stat n="2523" nulls="5" mean_count="841" sd="772.5" median_count="947" min_count="21" max_count="1555"/><enum code="N" count="1555">No</enum><enum code="Y" count="947">Yes</enum><enum code="D" count="21">Do not know</enum></stats></total></variable><variable id="phv00297362.v1.p1.c2" var_name="NHX7" calculated_type="enum_integer" reported_type=""><description>Q7. Memory problems [Neurological History Form]</description><total><subject_profile><sex><male>4</male><female>5</female></sex></subject_profile><stats><stat n="9" nulls="0" mean_count="4.5" sd="2.121" median_count="4.5" min_count="3" max_count="6"/><enum code="Y" count="6">Yes</enum><enum code="N" count="3">No</enum></stats></total></variable><variable id="phv00297363.v1.p1" var_name="NHX8" calculated_type="enum_integer" reported_type=""><description>Q8. Vision normal without glasses or contacts [Neurological History Form]</description><total><subject_profile><sex><male>1124</male><female>1406</female></sex></subject_profile><stats><stat n="2534" nulls="3" mean_count="844.7" sd="852.8" median_count="819" min_count="5" max_count="1710"/><enum code="N" count="1710">No</enum><enum code="Y" count="819">Yes</enum><enum code="D" count="5">Do not know</enum></stats></total></variable><variable id="phv00297363.v1.p1.c1" var_name="NHX8" calculated_type="enum_integer" reported_type=""><description>Q8. Vision normal without glasses or contacts [Neurological History Form]</description><total><subject_profile><sex><male>1120</male><female>1401</female></sex></subject_profile><stats><stat n="2525" nulls="3" mean_count="841.7" sd="849.3" median_count="817" min_count="5" max_count="1703"/><enum code="N" count="1703">No</enum><enum code="Y" count="817">Yes</enum><enum code="D" count="5">Do not know</enum></stats></total></variable><variable id="phv00297363.v1.p1.c2" var_name="NHX8" calculated_type="enum_integer" reported_type=""><description>Q8. Vision normal without glasses or contacts [Neurological History Form]</description><total><subject_profile><sex><male>4</male><female>5</female></sex></subject_profile><stats><stat n="9" nulls="0" mean_count="4.5" sd="3.536" median_count="4.5" min_count="2" max_count="7"/><enum code="N" count="7">No</enum><enum code="Y" count="2">Yes</enum></stats></total></variable><variable id="phv00297364.v1.p1" var_name="NHX9" calculated_type="enum_integer" reported_type=""><description>Q9. Usually wear glasses or contact lenses [Neurological History Form]</description><total><subject_profile><sex><male>1124</male><female>1406</female></sex></subject_profile><stats><stat n="2534" nulls="3" mean_count="844.7" sd="1020" median_count="554" min_count="2" max_count="1978"/><enum code="Y" count="1978">Yes</enum><enum code="N" count="554">No</enum><enum code="D" count="2">Do not know</enum></stats></total></variable><variable id="phv00297364.v1.p1.c1" var_name="NHX9" calculated_type="enum_integer" reported_type=""><description>Q9. Usually wear glasses or contact lenses [Neurological History Form]</description><total><subject_profile><sex><male>1120</male><female>1401</female></sex></subject_profile><stats><stat n="2525" nulls="3" mean_count="841.7" sd="1015" median_count="553" min_count="2" max_count="1970"/><enum code="Y" count="1970">Yes</enum><enum code="N" count="553">No</enum><enum code="D" count="2">Do not know</enum></stats></total></variable><variable id="phv00297364.v1.p1.c2" var_name="NHX9" calculated_type="enum_integer" reported_type=""><description>Q9. Usually wear glasses or contact lenses [Neurological History Form]</description><total><subject_profile><sex><male>4</male><female>5</female></sex></subject_profile><stats><stat n="9" nulls="0" mean_count="4.5" sd="4.95" median_count="4.5" min_count="1" max_count="8"/><enum code="Y" count="8">Yes</enum><enum code="N" count="1">No</enum></stats></total></variable><variable id="phv00297365.v1.p1" var_name="NHX9A" calculated_type="enum_integer" reported_type=""><description>Q9a. Vision normal with glasses or contacts [Neurological History Form]</description><total><subject_profile><sex><male>834</male><female>1116</female></sex></subject_profile><stats><stat n="1953" nulls="584" mean_count="651" sd="913.8" median_count="248" min_count="8" max_count="1697"/><enum code="Y" count="1697">Yes</enum><enum code="N" count="248">No</enum><enum code="D" count="8">Do not know</enum></stats></total></variable><variable id="phv00297365.v1.p1.c1" var_name="NHX9A" calculated_type="enum_integer" reported_type=""><description>Q9a. Vision normal with glasses or contacts [Neurological History Form]</description><total><subject_profile><sex><male>831</male><female>1111</female></sex></subject_profile><stats><stat n="1945" nulls="583" mean_count="648.3" sd="909.2" median_count="248" min_count="8" max_count="1689"/><enum code="Y" count="1689">Yes</enum><enum code="N" count="248">No</enum><enum code="D" count="8">Do not know</enum></stats></total></variable><variable id="phv00297365.v1.p1.c2" var_name="NHX9A" calculated_type="enum_integer" reported_type=""><description>Q9a. Vision normal with glasses or contacts [Neurological History Form]</description><total><subject_profile><sex><male>3</male><female>5</female></sex></subject_profile><stats><stat n="8" nulls="1"/><enum code="Y" count="8">Yes</enum></stats></total></variable><variable id="phv00297366.v1.p1" var_name="NHX10" calculated_type="enum_integer" reported_type=""><description>Q10. Hearing normal without aid(s) [Neurological History Form]</description><total><subject_profile><sex><male>1124</male><female>1404</female></sex></subject_profile><stats><stat n="2532" nulls="5" mean_count="844" sd="770.9" median_count="967" min_count="19" max_count="1546"/><enum code="Y" count="1546">Yes</enum><enum code="N" count="967">No</enum><enum code="D" count="19">Do not know</enum></stats></total></variable><variable id="phv00297366.v1.p1.c1" var_name="NHX10" calculated_type="enum_integer" reported_type=""><description>Q10. Hearing normal without aid(s) [Neurological History Form]</description><total><subject_profile><sex><male>1120</male><female>1399</female></sex></subject_profile><stats><stat n="2523" nulls="5" mean_count="841" sd="768.7" median_count="962" min_count="19" max_count="1542"/><enum code="Y" count="1542">Yes</enum><enum code="N" count="962">No</enum><enum code="D" count="19">Do not know</enum></stats></total></variable><variable id="phv00297366.v1.p1.c2" var_name="NHX10" calculated_type="enum_integer" reported_type=""><description>Q10. Hearing normal without aid(s) [Neurological History Form]</description><total><subject_profile><sex><male>4</male><female>5</female></sex></subject_profile><stats><stat n="9" nulls="0" mean_count="4.5" sd="0.7071" median_count="4.5" min_count="4" max_count="5"/><enum code="N" count="5">No</enum><enum code="Y" count="4">Yes</enum></stats></total></variable><variable id="phv00297367.v1.p1" var_name="NHX11" calculated_type="enum_integer" reported_type=""><description>Q11. Wear hearing aid(s) [Neurological History Form]</description><total><subject_profile><sex><male>1124</male><female>1404</female></sex></subject_profile><stats><stat n="2532" nulls="5" mean_count="844" sd="1158" median_count="366" min_count="1" max_count="2165"/><enum code="N" count="2165">No</enum><enum code="Y" count="366">Yes</enum><enum code="D" count="1">Do not know</enum></stats></total></variable><variable id="phv00297367.v1.p1.c1" var_name="NHX11" calculated_type="enum_integer" reported_type=""><description>Q11. Wear hearing aid(s) [Neurological History Form]</description><total><subject_profile><sex><male>1120</male><female>1399</female></sex></subject_profile><stats><stat n="2523" nulls="5" mean_count="841" sd="1155" median_count="364" min_count="1" max_count="2158"/><enum code="N" count="2158">No</enum><enum code="Y" count="364">Yes</enum><enum code="D" count="1">Do not know</enum></stats></total></variable><variable id="phv00297367.v1.p1.c2" var_name="NHX11" calculated_type="enum_integer" reported_type=""><description>Q11. Wear hearing aid(s) [Neurological History Form]</description><total><subject_profile><sex><male>4</male><female>5</female></sex></subject_profile><stats><stat n="9" nulls="0" mean_count="4.5" sd="3.536" median_count="4.5" min_count="2" max_count="7"/><enum code="N" count="7">No</enum><enum code="Y" count="2">Yes</enum></stats></total></variable><variable id="phv00297368.v1.p1" var_name="NHX11A" calculated_type="enum_integer" reported_type=""><description>Q11a. Hearing normal with aid(s) [Neurological History Form]</description><total><subject_profile><sex><male>220</male><female>144</female></sex></subject_profile><stats><stat n="364" nulls="2173" mean_count="121.3" sd="127" median_count="109" min_count="1" max_count="254"/><enum code="Y" count="254">Yes</enum><enum code="N" count="109">No</enum><enum code="D" count="1">Do not know</enum></stats></total></variable><variable id="phv00297368.v1.p1.c1" var_name="NHX11A" calculated_type="enum_integer" reported_type=""><description>Q11a. Hearing normal with aid(s) [Neurological History Form]</description><total><subject_profile><sex><male>219</male><female>143</female></sex></subject_profile><stats><stat n="362" nulls="2166" mean_count="120.7" sd="127.1" median_count="107" min_count="1" max_count="254"/><enum code="Y" count="254">Yes</enum><enum code="N" count="107">No</enum><enum code="D" count="1">Do not know</enum></stats></total></variable><variable id="phv00297368.v1.p1.c2" var_name="NHX11A" calculated_type="enum_integer" reported_type=""><description>Q11a. Hearing normal with aid(s) [Neurological History Form]</description><total><subject_profile><sex><male>1</male><female>1</female></sex></subject_profile><stats><stat n="2" nulls="7"/><enum code="N" count="2">No</enum></stats></total></variable><variable id="phv00297369.v1.p1" var_name="NHX12" calculated_type="enum_integer" reported_type=""><description>Q12. Sleepy most of the day [Neurological History Form]</description><total><subject_profile><sex><male>1122</male><female>1403</female></sex></subject_profile><stats><stat n="2529" nulls="8" mean_count="843" sd="1216" median_count="278" min_count="12" max_count="2239"/><enum code="N" count="2239">No</enum><enum code="Y" count="278">Yes</enum><enum code="D" count="12">Do not know</enum></stats></total></variable><variable id="phv00297369.v1.p1.c1" var_name="NHX12" calculated_type="enum_integer" reported_type=""><description>Q12. Sleepy most of the day [Neurological History Form]</description><total><subject_profile><sex><male>1118</male><female>1399</female></sex></subject_profile><stats><stat n="2521" nulls="7" mean_count="840.3" sd="1215" median_count="274" min_count="12" max_count="2235"/><enum code="N" count="2235">No</enum><enum code="Y" count="274">Yes</enum><enum code="D" count="12">Do not know</enum></stats></total></variable><variable id="phv00297369.v1.p1.c2" var_name="NHX12" calculated_type="enum_integer" reported_type=""><description>Q12. Sleepy most of the day [Neurological History Form]</description><total><subject_profile><sex><male>4</male><female>4</female></sex></subject_profile><stats><stat n="8" nulls="1" mean_count="4" sd="0" median_count="4" min_count="4" max_count="4"/><enum code="Y" count="4">Yes</enum><enum code="N" count="4">No</enum></stats></total></variable><variable id="phv00297370.v1.p1" var_name="NHX13" calculated_type="integer" reported_type=""><description>Q13. Days dozing off [Neurological History Form]</description><total><subject_profile><sex><male>1113</male><female>1391</female></sex></subject_profile><stats><stat n="2508" nulls="29" mean="5.915" sd="9.446" median="1" min="0" max="31"/><example count="997">0</example><example count="272">1</example><example count="235">2</example><example count="232">30</example><example count="132">4</example><example count="113">3</example><example count="100">5</example><example count="88">15</example><example count="73">10</example><example count="60">6</example></stats></total></variable><variable id="phv00297370.v1.p1.c1" var_name="NHX13" calculated_type="integer" reported_type=""><description>Q13. Days dozing off [Neurological History Form]</description><total><subject_profile><sex><male>1109</male><female>1387</female></sex></subject_profile><stats><stat n="2500" nulls="28" mean="5.922" sd="9.46" median="1" min="0" max="31"/><example count="996">0</example><example count="272">1</example><example count="233">2</example><example count="232">30</example><example count="130">4</example><example count="113">3</example><example count="99">5</example><example count="88">15</example><example count="73">10</example><example count="58">6</example></stats></total></variable><variable id="phv00297370.v1.p1.c2" var_name="NHX13" calculated_type="integer" reported_type=""><description>Q13. Days dozing off [Neurological History Form]</description><total><subject_profile><sex><male>4</male><female>4</female></sex></subject_profile><stats><stat n="8" nulls="1" mean="3.625" sd="2.134" median="4" min="0" max="6"/><enum count="2">6</enum><enum count="2">2</enum><enum count="2">4</enum><enum count="1">0</enum><enum count="1">5</enum></stats></total></variable><variable id="phv00297371.v1.p1" var_name="NHX14" calculated_type="enum_integer" reported_type=""><description>Q14. Sleepy most of the day [Neurological History Form]</description><total><subject_profile><sex><male>1122</male><female>1402</female></sex></subject_profile><stats><stat n="2528" nulls="9" mean_count="842.7" sd="1193" median_count="282" min_count="33" max_count="2213"/><enum code="N" count="2213">No</enum><enum code="Y" count="282">Yes</enum><enum code="D" count="33">Do not know</enum></stats></total></variable><variable id="phv00297371.v1.p1.c1" var_name="NHX14" calculated_type="enum_integer" reported_type=""><description>Q14. Sleepy most of the day [Neurological History Form]</description><total><subject_profile><sex><male>1118</male><female>1398</female></sex></subject_profile><stats><stat n="2520" nulls="8" mean_count="840" sd="1190" median_count="280" min_count="33" max_count="2207"/><enum code="N" count="2207">No</enum><enum code="Y" count="280">Yes</enum><enum code="D" count="33">Do not know</enum></stats></total></variable><variable id="phv00297371.v1.p1.c2" var_name="NHX14" calculated_type="enum_integer" reported_type=""><description>Q14. Sleepy most of the day [Neurological History Form]</description><total><subject_profile><sex><male>4</male><female>4</female></sex></subject_profile><stats><stat n="8" nulls="1" mean_count="4" sd="2.828" median_count="4" min_count="2" max_count="6"/><enum code="N" count="6">No</enum><enum code="Y" count="2">Yes</enum></stats></total></variable><variable id="phv00297372.v1.p1" var_name="NHX14A" calculated_type="enum_integer" reported_type=""><description>Q14a. How often sleepy most of the day [Neurological History Form]</description><total><subject_profile><sex><male>151</male><female>130</female></sex></subject_profile><stats><stat n="281" nulls="2256" mean_count="46.83" sd="23.93" median_count="45" min_count="17" max_count="73"/><enum code="2" count="73">Less than once a month</enum><enum code="1" count="73">Less that three times in total</enum><enum code="3" count="56">1-3 times a month</enum><enum code="D" count="34">Do not know</enum><enum code="5" count="28">More than once per week</enum><enum code="4" count="17">Once a week</enum></stats></total></variable><variable id="phv00297372.v1.p1.c1" var_name="NHX14A" calculated_type="enum_integer" reported_type=""><description>Q14a. How often sleepy most of the day [Neurological History Form]</description><total><subject_profile><sex><male>150</male><female>129</female></sex></subject_profile><stats><stat n="279" nulls="2249" mean_count="46.5" sd="23.96" median_count="44" min_count="17" max_count="73"/><enum code="2" count="73">Less than once a month</enum><enum code="1" count="73">Less that three times in total</enum><enum code="3" count="55">1-3 times a month</enum><enum code="D" count="33">Do not know</enum><enum code="5" count="28">More than once per week</enum><enum code="4" count="17">Once a week</enum></stats></total></variable><variable id="phv00297372.v1.p1.c2" var_name="NHX14A" calculated_type="enum_integer" reported_type=""><description>Q14a. How often sleepy most of the day [Neurological History Form]</description><total><subject_profile><sex><male>1</male><female>1</female></sex></subject_profile><stats><stat n="2" nulls="7" mean_count="1" sd="0" median_count="1" min_count="1" max_count="1"/><enum code="D" count="1">Do not know</enum><enum code="3" count="1">1-3 times a month</enum></stats></total></variable><variable id="phv00297373.v1.p1" var_name="NHX14B" calculated_type="integer" units="Years" reported_type=""><description>Q14b. Age when sleepy started [Neurological History Form]</description><total><subject_profile><sex><male>120</male><female>103</female></sex></subject_profile><stats><stat n="223" nulls="2314" mean="53.19" sd="24.36" median="60" min="0" max="88"/><example count="21">60</example><example count="18">70</example><example count="10">40</example><example count="9">55</example><example count="9">65</example><example count="8">81</example><example count="8">50</example><example count="7">30</example><example count="6">74</example><example count="6">79</example></stats></total></variable><variable id="phv00297373.v1.p1.c1" var_name="NHX14B" calculated_type="integer" units="Years" reported_type=""><description>Q14b. Age when sleepy started [Neurological History Form]</description><total><subject_profile><sex><male>119</male><female>102</female></sex></subject_profile><stats><stat n="221" nulls="2307" mean="53.23" sd="24.29" median="60" min="0" max="88"/><example count="21">60</example><example count="18">70</example><example count="10">40</example><example count="9">55</example><example count="9">65</example><example count="8">50</example><example count="7">81</example><example count="7">30</example><example count="6">74</example><example count="6">79</example></stats></total></variable><variable id="phv00297373.v1.p1.c2" var_name="NHX14B" calculated_type="integer" units="Years" reported_type=""><description>Q14b. Age when sleepy started [Neurological History Form]</description><total><subject_profile><sex><male>1</male><female>1</female></sex></subject_profile><stats><stat n="2" nulls="7" mean="49.5" sd="44.55" median="49.5" min="18" max="81"/><enum count="1">18</enum><enum count="1">81</enum></stats></total></variable><variable id="phv00297374.v1.p1" var_name="NHX15" calculated_type="enum_integer" reported_type=""><description>Q15. Shaking in limbs [Neurological History Form]</description><total><subject_profile><sex><male>1123</male><female>1406</female></sex></subject_profile><stats><stat n="2533" nulls="4" mean_count="844.3" sd="1221" median_count="277" min_count="10" max_count="2246"/><enum code="N" count="2246">No</enum><enum code="Y" count="277">Yes</enum><enum code="D" count="10">Do not know</enum></stats></total></variable><variable id="phv00297374.v1.p1.c1" var_name="NHX15" calculated_type="enum_integer" reported_type=""><description>Q15. Shaking in limbs [Neurological History Form]</description><total><subject_profile><sex><male>1119</male><female>1402</female></sex></subject_profile><stats><stat n="2525" nulls="3" mean_count="841.7" sd="1217" median_count="276" min_count="10" max_count="2239"/><enum code="N" count="2239">No</enum><enum code="Y" count="276">Yes</enum><enum code="D" count="10">Do not know</enum></stats></total></variable><variable id="phv00297374.v1.p1.c2" var_name="NHX15" calculated_type="enum_integer" reported_type=""><description>Q15. Shaking in limbs [Neurological History Form]</description><total><subject_profile><sex><male>4</male><female>4</female></sex></subject_profile><stats><stat n="8" nulls="1" mean_count="4" sd="4.243" median_count="4" min_count="1" max_count="7"/><enum code="N" count="7">No</enum><enum code="Y" count="1">Yes</enum></stats></total></variable><variable id="phv00297375.v1.p1" var_name="NHX15A" calculated_type="integer" reported_type=""><description>Q15a. Age when shaking started [Neurological History Form]</description><total><subject_profile><sex><male>113</male><female>145</female></sex></subject_profile><stats><stat n="258" nulls="2279" mean="66.1" sd="18.35" median="70" min="0" max="89"/><example count="21">70</example><example count="20">75</example><example count="16">65</example><example count="16">60</example><example count="12">79</example><example count="11">77</example><example count="10">80</example><example count="9">84</example><example count="9">73</example><example count="8">67</example></stats></total></variable><variable id="phv00297375.v1.p1.c1" var_name="NHX15A" calculated_type="integer" reported_type=""><description>Q15a. Age when shaking started [Neurological History Form]</description><total><subject_profile><sex><male>112</male><female>145</female></sex></subject_profile><stats><stat n="257" nulls="2271" mean="66.09" sd="18.38" median="70" min="0" max="89"/><example count="20">70</example><example count="20">75</example><example count="16">65</example><example count="16">60</example><example count="12">79</example><example count="11">77</example><example count="10">80</example><example count="9">84</example><example count="9">73</example><example count="8">67</example></stats></total></variable><variable id="phv00297375.v1.p1.c2" var_name="NHX15A" calculated_type="integer" reported_type=""><description>Q15a. Age when shaking started [Neurological History Form]</description><total><subject_profile><sex><male>1</male></sex></subject_profile><stats><stat n="1" nulls="8" mean="70" median="70" min="70" max="70"/><enum count="1">70</enum></stats></total></variable><variable id="phv00297376.v1.p1" var_name="NHX16" calculated_type="enum_integer" reported_type=""><description>Q16. Smaller hand writing [Neurological History Form]</description><total><subject_profile><sex><male>1122</male><female>1403</female></sex></subject_profile><stats><stat n="2529" nulls="8" mean_count="843" sd="1074" median_count="390" min_count="70" max_count="2069"/><enum code="N" count="2069">No</enum><enum code="Y" count="390">Yes</enum><enum code="D" count="70">Do not know</enum></stats></total></variable><variable id="phv00297376.v1.p1.c1" var_name="NHX16" calculated_type="enum_integer" reported_type=""><description>Q16. Smaller hand writing [Neurological History Form]</description><total><subject_profile><sex><male>1118</male><female>1399</female></sex></subject_profile><stats><stat n="2521" nulls="7" mean_count="840.3" sd="1072" median_count="387" min_count="70" max_count="2064"/><enum code="N" count="2064">No</enum><enum code="Y" count="387">Yes</enum><enum code="D" count="70">Do not know</enum></stats></total></variable><variable id="phv00297376.v1.p1.c2" var_name="NHX16" calculated_type="enum_integer" reported_type=""><description>Q16. Smaller hand writing [Neurological History Form]</description><total><subject_profile><sex><male>4</male><female>4</female></sex></subject_profile><stats><stat n="8" nulls="1" mean_count="4" sd="1.414" median_count="4" min_count="3" max_count="5"/><enum code="N" count="5">No</enum><enum code="Y" count="3">Yes</enum></stats></total></variable><variable id="phv00297377.v1.p1" var_name="NHX0AY" calculated_type="integer" reported_type=""><description>Q0a. Year of completion date [Neurological History Form]</description><total><subject_profile><sex><male>1125</male><female>1408</female></sex></subject_profile><stats><stat n="2537" nulls="0" mean="2012" sd="0.6538" median="2012" min="2011" max="2013"/><enum count="1197">2012</enum><enum count="1073">2013</enum><enum count="267">2011</enum></stats></total></variable><variable id="phv00297377.v1.p1.c1" var_name="NHX0AY" calculated_type="integer" reported_type=""><description>Q0a. Year of completion date [Neurological History Form]</description><total><subject_profile><sex><male>1121</male><female>1403</female></sex></subject_profile><stats><stat n="2528" nulls="0" mean="2012" sd="0.6537" median="2012" min="2011" max="2013"/><enum count="1193">2012</enum><enum count="1069">2013</enum><enum count="266">2011</enum></stats></total></variable><variable id="phv00297377.v1.p1.c2" var_name="NHX0AY" calculated_type="integer" reported_type=""><description>Q0a. Year of completion date [Neurological History Form]</description><total><subject_profile><sex><male>4</male><female>5</female></sex></subject_profile><stats><stat n="9" nulls="0" mean="2012" sd="0.7071" median="2012" min="2011" max="2013"/><enum count="4">2012</enum><enum count="4">2013</enum><enum count="1">2011</enum></stats></total></variable><variable id="phv00297378.v1.p1" var_name="NHX4D" calculated_type="enum_integer" reported_type=""><description>Q4d. Stroke or cerebrovascular accident [Neurological History Form]</description><total><subject_profile><sex><male>138</male><female>155</female></sex></subject_profile><stats><stat n="295" nulls="2242" mean_count="147.5" sd="96.87" median_count="147.5" min_count="79" max_count="216"/><enum code="Y" count="216">Yes</enum><enum code="N" count="79">No</enum></stats></total></variable><variable id="phv00297378.v1.p1.c1" var_name="NHX4D" calculated_type="enum_integer" reported_type=""><description>Q4d. Stroke or cerebrovascular accident [Neurological History Form]</description><total><subject_profile><sex><male>138</male><female>155</female></sex></subject_profile><stats><stat n="295" nulls="2233" mean_count="147.5" sd="96.87" median_count="147.5" min_count="79" max_count="216"/><enum code="Y" count="216">Yes</enum><enum code="N" count="79">No</enum></stats></total></variable><variable id="phv00297378.v1.p1.c2" var_name="NHX4D" calculated_type="enum_integer" reported_type=""><description>Q4d. Stroke or cerebrovascular accident [Neurological History Form]</description><total><stats><stat n="0" nulls="9"/></stats></total></variable><variable id="phv00297379.v1.p1" var_name="NHX4D1" calculated_type="integer" units="Years" reported_type=""><description>Q4d1. Stroke or cerebrovascular age at diagnosis [Neurological History Form]</description><total><subject_profile><sex><male>101</male><female>100</female></sex></subject_profile><stats><stat n="203" nulls="2334" mean="69.97" sd="9.462" median="70" min="35" max="89"/><example count="20">70</example><example count="11">65</example><example count="9">74</example><example count="9">72</example><example count="8">77</example><example count="8">68</example><example count="8">69</example><example count="8">75</example><example count="6">71</example><example count="6">67</example></stats></total></variable><variable id="phv00297379.v1.p1.c1" var_name="NHX4D1" calculated_type="integer" units="Years" reported_type=""><description>Q4d1. Stroke or cerebrovascular age at diagnosis [Neurological History Form]</description><total><subject_profile><sex><male>101</male><female>100</female></sex></subject_profile><stats><stat n="203" nulls="2325" mean="69.97" sd="9.462" median="70" min="35" max="89"/><example count="20">70</example><example count="11">65</example><example count="9">74</example><example count="9">72</example><example count="8">77</example><example count="8">68</example><example count="8">69</example><example count="8">75</example><example count="6">71</example><example count="6">67</example></stats></total></variable><variable id="phv00297379.v1.p1.c2" var_name="NHX4D1" calculated_type="integer" units="Years" reported_type=""><description>Q4d1. Stroke or cerebrovascular age at diagnosis [Neurological History Form]</description><total><stats><stat n="0" nulls="9"/></stats></total></variable></data_table>
